Workbook
Name MARGEM_ESTRATEGICA: '00-Parametros'!$C$5
Name MARGEM_COMERCIAL: '00-Parametros'!$C$6
Name MARGEM_NEGOCIACAO: '00-Parametros'!$C$7
Name MARGEM_LP: '00-Parametros'!$C$8
Name IMPOSTOS_PCT: '00-Parametros'!$C$9
Name COMISSAO_PADRAO_PCT: '00-Parametros'!$C$10
Name MARKETING_PROVISIONADO_PCT: '00-Parametros'!$C$11
Name RESERVA_FINANCEIRA_PCT: '00-Parametros'!$C$12
Name TAXA_FINANCEIRA_MENSAL: '00-Parametros'!$C$13
Name TAXA_OPORTUNIDADE_MENSAL: '00-Parametros'!$C$14
Name DIAS_ESTOQUE_META: '00-Parametros'!$C$15
Name CUSTO_OPERACIONAL_RATEIO_UNITARIO: '00-Parametros'!$C$16
Name FASE1_MAX_DIAS: '00-Parametros'!$C$17
Name FASE2_MAX_DIAS: '00-Parametros'!$C$18
Name FASE3_MAX_DIAS: '00-Parametros'!$C$19
Name SAUDE_PREMIUM_MAX_DIAS: '00-Parametros'!$C$20
Name SAUDE_SAUDAVEL_MAX_DIAS: '00-Parametros'!$C$21
Name SAUDE_ATENCAO_MAX_DIAS: '00-Parametros'!$C$22
Name DEPRECIACAO_MENSAL_CATEGORIA_PCT: '00-Parametros'!$C$23

Sheet 00-Leia-me
A1: MM NEGÓCIOS VEÍCULOS — Engenharia de Precificação de Motocicletas
A2: Planilha operacional. Acompanha o manual: ENGENHARIA-PRECIFICACAO-MOTOS-MM.md
B5: COMO USAR ESTA PLANILHA
B7: 1. Calibre a aba 00-Parametros primeiro (margens, taxas, impostos, faixas de dias).
B8: Todas as demais abas leem esses valores — nada é digitado duas vezes.
B9: 2. Cadastre a moto assim que ela entrar no estoque, na aba 01-Cadastro-Motos.
B10: 3. Lance os custos diretos (revisão, estética, documentação, frete, combustível,
B11: acessórios) na aba 02-Custos-Diretos assim que ocorrerem.
B12: 4. Se houver campanha de marketing específica para a moto, lance verba/leads/cliques
B13: na aba 03-Marketing.
B14: 5. A aba 06-Precificacao calcula sozinha: Custo Base e os 4 preços
B15: (Estratégico / Comercial / Negociação / LP). Não editar as colunas de fórmula.
B16: 6. A aba 07-Estoque-Dinamica calcula sozinha a fase (1 a 4), a classificação de
B17: saúde do estoque e o preço sugerido do dia, com base na data de hoje.
... B37: Para ampliar, arraste as fórmulas da última linha preenchida para baixo.

Sheet 00-Parametros
A1: Parâmetros da Empresa
A2: Fonte única de verdade — todas as fórmulas leem daqui.
A4: # | B4: Parâmetro | C4: Valor | D4: Observação
A5: 1 | B5: MARGEM_ESTRATEGICA | C5: 0.25 | D5: % aplicado no divisor — Fase 1 / motos de alta procura
A6: 2 | B6: MARGEM_COMERCIAL | C6: 0.16 | D6: % aplicado no divisor — preço-padrão da casa
A7: 3 | B7: MARGEM_NEGOCIACAO | C7: 0.09 | D7: % aplicado no divisor — última concessão sem aprovação
A8: 4 | B8: MARGEM_LP | C8: 0.04 | D8: % aplicado no divisor — piso absoluto (Lucro Presumido)
A9: 5 | B9: IMPOSTOS_PCT | C9: 0.06 | D9: Alíquota efetiva sobre a venda
A10: 6 | B10: COMISSAO_PADRAO_PCT | C10: 0.03 | D10: Comissão padrão do vendedor sobre o preço vendido
A11: 7 | B11: MARKETING_PROVISIONADO_PCT | C11: 0.025 | D11: Verba de marketing provisionada, % do preço
A12: 8 | B12: RESERVA_FINANCEIRA_PCT | C12: 0.02 | D12: Contingência/reserva financeira, % do preço
A13: 9 | B13: TAXA_FINANCEIRA_MENSAL | C13: 0.02 | D13: Custo de capital (financiado ou próprio), ao mês
A14: 10 | B14: TAXA_OPORTUNIDADE_MENSAL | C14: 0.015 | D14: Custo de oportunidade do capital próprio, ao mês
A15: 11 | B15: DIAS_ESTOQUE_META | C15: 45 | D15: Giro médio esperado (dias) — usado na precificação inicial
A16: 12 | B16: CUSTO_OPERACIONAL_RATEIO_UNITARIO | C16: 180 | D16: Despesas fixas do mês ÷ nº médio de motos vendidas/mês
... A23: 19 | B23: DEPRECIACAO_MENSAL_CATEGORIA_PCT | C23: 0.01 | D23: Depreciação estimada de mercado ao mês, motos >90 dias

Sheet 01-Cadastro-Motos
A1: Cadastro de Motocicletas
A3: ID Moto | B3: Modelo | C3: Marca | D3: Ano | E3: Placa | F3: KM | G3: Categoria (giro) | H3: Data Compra | I3: Valor Compra (R$) | J3: Condição | K3: Status | L3: ID Vendedor Cadastro | M3: Data Venda | N3: Preço Venda Real (R$) | O3: ID Vendedor Venda | P3: Dias em Estoque
A4: MOTO-001 | B4: Honda CG 160 Titan 2022 | C4: Honda | D4: 2022 | E4: ABC1D23 | F4: 8200 | G4: Giro Médio | H4: 46166 | I4: 9500 | J4: Boa | K4: Em Estoque | L4: VEND-01 | P4: =IF($H4="","",IF($K4="Vendida",IF($M4="","",$M4-$H4),TODAY()-$H4))
A5: MOTO-002 | B5: Yamaha Fazer 250 2021 | C5: Yamaha | D5: 2021 | E5: XYZ2E45 | F5: 15300 | G5: Giro Alto | H5: 46147 | I5: 11000 | J5: Boa | K5: Vendida | L5: VEND-02 | M5: 46187 | N5: 16000 | O5: VEND-02 | P5: =IF($H5="","",IF($K5="Vendida",IF($M5="","",$M5-$H5),TODAY()-$H5))
P6: =IF($H6="","",IF($K6="Vendida",IF($M6="","",$M6-$H6),TODAY()-$H6))
P7: =IF($H7="","",IF($K7="Vendida",IF($M7="","",$M7-$H7),TODAY()-$H7))
P8: =IF($H8="","",IF($K8="Vendida",IF($M8="","",$M8-$H8),TODAY()-$H8))
P9: =IF($H9="","",IF($K9="Vendida",IF($M9="","",$M9-$H9),TODAY()-$H9))
P10: =IF($H10="","",IF($K10="Vendida",IF($M10="","",$M10-$H10),TODAY()-$H10))
P11: =IF($H11="","",IF($K11="Vendida",IF($M11="","",$M11-$H11),TODAY()-$H11))
P12: =IF($H12="","",IF($K12="Vendida",IF($M12="","",$M12-$H12),TODAY()-$H12))
P13: =IF($H13="","",IF($K13="Vendida",IF($M13="","",$M13-$H13),TODAY()-$H13))
P14: =IF($H14="","",IF($K14="Vendida",IF($M14="","",$M14-$H14),TODAY()-$H14))
P15: =IF($H15="","",IF($K15="Vendida",IF($M15="","",$M15-$H15),TODAY()-$H15))
P16: =IF($H16="","",IF($K16="Vendida",IF($M16="","",$M16-$H16),TODAY()-$H16))
P17: =IF($H17="","",IF($K17="Vendida",IF($M17="","",$M17-$H17),TODAY()-$H17))
... P123: =IF($H123="","",IF($K123="Vendida",IF($M123="","",$M123-$H123),TODAY()-$H123))

Sheet 02-Custos-Diretos
A1: Custos Diretos de Preparação (por moto)
A3: ID Moto | B3: Modelo (auto) | C3: Revisão (R$) | D3: Estética (R$) | E3: Documentação (R$) | F3: Frete (R$) | G3: Combustível (R$) | H3: Acessórios (R$) | I3: Outros (R$) | J3: Total Custos Diretos (R$)
A4: MOTO-001 | B4: =IF($A4="","",IFERROR(INDEX('01-Cadastro-Motos'!$B$4:$B$123,MATCH($A4,'01-Cadastro-Motos'!$A$4:$A$123,0)),"")) | C4: 200 | D4: 150 | E4: 100 | F4: 0 | G4: 0 | H4: 0 | I4: 0 | J4: =IF($A4="","",SUM(C4:I4))
A5: MOTO-002 | B5: =IF($A5="","",IFERROR(INDEX('01-Cadastro-Motos'!$B$4:$B$123,MATCH($A5,'01-Cadastro-Motos'!$A$4:$A$123,0)),"")) | C5: 250 | D5: 100 | E5: 90 | F5: 0 | G5: 0 | H5: 60 | I5: 0 | J5: =IF($A5="","",SUM(C5:I5))
B6: =IF($A6="","",IFERROR(INDEX('01-Cadastro-Motos'!$B$4:$B$123,MATCH($A6,'01-Cadastro-Motos'!$A$4:$A$123,0)),"")) | J6: =IF($A6="","",SUM(C6:I6))
B7: =IF($A7="","",IFERROR(INDEX('01-Cadastro-Motos'!$B$4:$B$123,MATCH($A7,'01-Cadastro-Motos'!$A$4:$A$123,0)),"")) | J7: =IF($A7="","",SUM(C7:I7))
B8: =IF($A8="","",IFERROR(INDEX('01-Cadastro-Motos'!$B$4:$B$123,MATCH($A8,'01-Cadastro-Motos'!$A$4:$A$123,0)),"")) | J8: =IF($A8="","",SUM(C8:I8))
B9: =IF($A9="","",IFERROR(INDEX('01-Cadastro-Motos'!$B$4:$B$123,MATCH($A9,'01-Cadastro-Motos'!$A$4:$A$123,0)),"")) | J9: =IF($A9="","",SUM(C9:I9))
B10: =IF($A10="","",IFERROR(INDEX('01-Cadastro-Motos'!$B$4:$B$123,MATCH($A10,'01-Cadastro-Motos'!$A$4:$A$123,0)),"")) | J10: =IF($A10="","",SUM(C10:I10))
B11: =IF($A11="","",IFERROR(INDEX('01-Cadastro-Motos'!$B$4:$B$123,MATCH($A11,'01-Cadastro-Motos'!$A$4:$A$123,0)),"")) | J11: =IF($A11="","",SUM(C11:I11))
B12: =IF($A12="","",IFERROR(INDEX('01-Cadastro-Motos'!$B$4:$B$123,MATCH($A12,'01-Cadastro-Motos'!$A$4:$A$123,0)),"")) | J12: =IF($A12="","",SUM(C12:I12))
B13: =IF($A13="","",IFERROR(INDEX('01-Cadastro-Motos'!$B$4:$B$123,MATCH($A13,'01-Cadastro-Motos'!$A$4:$A$123,0)),"")) | J13: =IF($A13="","",SUM(C13:I13))
B14: =IF($A14="","",IFERROR(INDEX('01-Cadastro-Motos'!$B$4:$B$123,MATCH($A14,'01-Cadastro-Motos'!$A$4:$A$123,0)),"")) | J14: =IF($A14="","",SUM(C14:I14))
B15: =IF($A15="","",IFERROR(INDEX('01-Cadastro-Motos'!$B$4:$B$123,MATCH($A15,'01-Cadastro-Motos'!$A$4:$A$123,0)),"")) | J15: =IF($A15="","",SUM(C15:I15))
B16: =IF($A16="","",IFERROR(INDEX('01-Cadastro-Motos'!$B$4:$B$123,MATCH($A16,'01-Cadastro-Motos'!$A$4:$A$123,0)),"")) | J16: =IF($A16="","",SUM(C16:I16))
B17: =IF($A17="","",IFERROR(INDEX('01-Cadastro-Motos'!$B$4:$B$123,MATCH($A17,'01-Cadastro-Motos'!$A$4:$A$123,0)),"")) | J17: =IF($A17="","",SUM(C17:I17))
... B123: =IF($A123="","",IFERROR(INDEX('01-Cadastro-Motos'!$B$4:$B$123,MATCH($A123,'01-Cadastro-Motos'!$A$4:$A$123,0)),"")) | J123: =IF($A123="","",SUM(C123:I123))

Sheet 03-Marketing
A1: Marketing por Motocicleta / Campanha
A3: ID Moto | B3: Modelo (auto) | C3: Verba Investida Real (R$) | D3: Leads Gerados | E3: Cliques | F3: Vendas Atribuídas | G3: CPL (R$) | H3: CPC (R$) | I3: CAC (R$)
A4: MOTO-001 | B4: =IF($A4="","",IFERROR(INDEX('01-Cadastro-Motos'!$B$4:$B$123,MATCH($A4,'01-Cadastro-Motos'!$A$4:$A$123,0)),"")) | C4: 120 | D4: 18 | E4: 340 | F4: 1 | G4: =IF(OR($A4="",$D4=0),"",$C4/$D4) | H4: =IF(OR($A4="",$E4=0),"",$C4/$E4) | I4: =IF(OR($A4="",$F4=0),"",$C4/$F4)
A5: MOTO-002 | B5: =IF($A5="","",IFERROR(INDEX('01-Cadastro-Motos'!$B$4:$B$123,MATCH($A5,'01-Cadastro-Motos'!$A$4:$A$123,0)),"")) | C5: 0 | D5: 0 | E5: 0 | F5: 0 | G5: =IF(OR($A5="",$D5=0),"",$C5/$D5) | H5: =IF(OR($A5="",$E5=0),"",$C5/$E5) | I5: =IF(OR($A5="",$F5=0),"",$C5/$F5)
B6: =IF($A6="","",IFERROR(INDEX('01-Cadastro-Motos'!$B$4:$B$123,MATCH($A6,'01-Cadastro-Motos'!$A$4:$A$123,0)),"")) | G6: =IF(OR($A6="",$D6=0),"",$C6/$D6) | H6: =IF(OR($A6="",$E6=0),"",$C6/$E6) | I6: =IF(OR($A6="",$F6=0),"",$C6/$F6)
B7: =IF($A7="","",IFERROR(INDEX('01-Cadastro-Motos'!$B$4:$B$123,MATCH($A7,'01-Cadastro-Motos'!$A$4:$A$123,0)),"")) | G7: =IF(OR($A7="",$D7=0),"",$C7/$D7) | H7: =IF(OR($A7="",$E7=0),"",$C7/$E7) | I7: =IF(OR($A7="",$F7=0),"",$C7/$F7)
B8: =IF($A8="","",IFERROR(INDEX('01-Cadastro-Motos'!$B$4:$B$123,MATCH($A8,'01-Cadastro-Motos'!$A$4:$A$123,0)),"")) | G8: =IF(OR($A8="",$D8=0),"",$C8/$D8) | H8: =IF(OR($A8="",$E8=0),"",$C8/$E8) | I8: =IF(OR($A8="",$F8=0),"",$C8/$F8)
B9: =IF($A9="","",IFERROR(INDEX('01-Cadastro-Motos'!$B$4:$B$123,MATCH($A9,'01-Cadastro-Motos'!$A$4:$A$123,0)),"")) | G9: =IF(OR($A9="",$D9=0),"",$C9/$D9) | H9: =IF(OR($A9="",$E9=0),"",$C9/$E9) | I9: =IF(OR($A9="",$F9=0),"",$C9/$F9)
B10: =IF($A10="","",IFERROR(INDEX('01-Cadastro-Motos'!$B$4:$B$123,MATCH($A10,'01-Cadastro-Motos'!$A$4:$A$123,0)),"")) | G10: =IF(OR($A10="",$D10=0),"",$C10/$D10) | H10: =IF(OR($A10="",$E10=0),"",$C10/$E10) | I10: =IF(OR($A10="",$F10=0),"",$C10/$F10)
B11: =IF($A11="","",IFERROR(INDEX('01-Cadastro-Motos'!$B$4:$B$123,MATCH($A11,'01-Cadastro-Motos'!$A$4:$A$123,0)),"")) | G11: =IF(OR($A11="",$D11=0),"",$C11/$D11) | H11: =IF(OR($A11="",$E11=0),"",$C11/$E11) | I11: =IF(OR($A11="",$F11=0),"",$C11/$F11)
B12: =IF($A12="","",IFERROR(INDEX('01-Cadastro-Motos'!$B$4:$B$123,MATCH($A12,'01-Cadastro-Motos'!$A$4:$A$123,0)),"")) | G12: =IF(OR($A12="",$D12=0),"",$C12/$D12) | H12: =IF(OR($A12="",$E12=0),"",$C12/$E12) | I12: =IF(OR($A12="",$F12=0),"",$C12/$F12)
B13: =IF($A13="","",IFERROR(INDEX('01-Cadastro-Motos'!$B$4:$B$123,MATCH($A13,'01-Cadastro-Motos'!$A$4:$A$123,0)),"")) | G13: =IF(OR($A13="",$D13=0),"",$C13/$D13) | H13: =IF(OR($A13="",$E13=0),"",$C13/$E13) | I13: =IF(OR($A13="",$F13=0),"",$C13/$F13)
B14: =IF($A14="","",IFERROR(INDEX('01-Cadastro-Motos'!$B$4:$B$123,MATCH($A14,'01-Cadastro-Motos'!$A$4:$A$123,0)),"")) | G14: =IF(OR($A14="",$D14=0),"",$C14/$D14) | H14: =IF(OR($A14="",$E14=0),"",$C14/$E14) | I14: =IF(OR($A14="",$F14=0),"",$C14/$F14)
B15: =IF($A15="","",IFERROR(INDEX('01-Cadastro-Motos'!$B$4:$B$123,MATCH($A15,'01-Cadastro-Motos'!$A$4:$A$123,0)),"")) | G15: =IF(OR($A15="",$D15=0),"",$C15/$D15) | H15: =IF(OR($A15="",$E15=0),"",$C15/$E15) | I15: =IF(OR($A15="",$F15=0),"",$C15/$F15)
B16: =IF($A16="","",IFERROR(INDEX('01-Cadastro-Motos'!$B$4:$B$123,MATCH($A16,'01-Cadastro-Motos'!$A$4:$A$123,0)),"")) | G16: =IF(OR($A16="",$D16=0),"",$C16/$D16) | H16: =IF(OR($A16="",$E16=0),"",$C16/$E16) | I16: =IF(OR($A16="",$F16=0),"",$C16/$F16)
B17: =IF($A17="","",IFERROR(INDEX('01-Cadastro-Motos'!$B$4:$B$123,MATCH($A17,'01-Cadastro-Motos'!$A$4:$A$123,0)),"")) | G17: =IF(OR($A17="",$D17=0),"",$C17/$D17) | H17: =IF(OR($A17="",$E17=0),"",$C17/$E17) | I17: =IF(OR($A17="",$F17=0),"",$C17/$F17)
... B123: =IF($A123="","",IFERROR(INDEX('01-Cadastro-Motos'!$B$4:$B$123,MATCH($A123,'01-Cadastro-Motos'!$A$4:$A$123,0)),"")) | G123: =IF(OR($A123="",$D123=0),"",$C123/$D123) | H123: =IF(OR($A123="",$E123=0),"",$C123/$E123) | I123: =IF(OR($A123="",$F123=0),"",$C123/$F123)

Sheet 04-Comercial
A1: Cadastro de Vendedores
A3: ID Vendedor | B3: Nome | C3: Comissão Padrão (%) | D3: Meta Mensal (R$) | E3: Data Admissão
A4: VEND-01 | B4: João Vendedor | C4: 0.03 | D4: 60000 | E4: 45689
A5: VEND-02 | B5: Maria Vendedora | C5: 0.03 | D5: 60000 | E5: 45823
A6: VEND-03 | B6: Carlos Vendedor | C6: 0.03 | D6: 60000 | E6: 46032

Sheet 05-Financeiro
A1: Reconciliação Financeira Real (Pilar 8.3 / 8.4 / 8.13)
A3: ID Moto | B3: Modelo (auto) | C3: Valor Compra (auto) | D3: Dias em Estoque (auto) | E3: Custo Financeiro Real (R$) | F3: Custo Oportunidade Real (R$) | G3: Precisão de Giro
A4: =IF('01-Cadastro-Motos'!$A4="","",'01-Cadastro-Motos'!$A4) | B4: =IF($A4="","",IFERROR(INDEX('01-Cadastro-Motos'!$B$4:$B$123,MATCH($A4,'01-Cadastro-Motos'!$A$4:$A$123,0)),"")) | C4: =IF($A4="","",IFERROR(INDEX('01-Cadastro-Motos'!$I$4:$I$123,MATCH($A4,'01-Cadastro-Motos'!$A$4:$A$123,0)),"")) | D4: =IF($A4="","",IFERROR(INDEX('01-Cadastro-Motos'!$P$4:$P$123,MATCH($A4,'01-Cadastro-Motos'!$A$4:$A$123,0)),"")) | E4: =IF(OR($A4="",$D4=""),"",$C4*'00-Parametros'!$C$13*($D4/30)) | F4: =IF(OR($A4="",$D4=""),"",$C4*'00-Parametros'!$C$14*($D4/30)) | G4: =IF(OR($A4="",$D4="",$D4=0),"",'00-Parametros'!$C$15/$D4)
A5: =IF('01-Cadastro-Motos'!$A5="","",'01-Cadastro-Motos'!$A5) | B5: =IF($A5="","",IFERROR(INDEX('01-Cadastro-Motos'!$B$4:$B$123,MATCH($A5,'01-Cadastro-Motos'!$A$4:$A$123,0)),"")) | C5: =IF($A5="","",IFERROR(INDEX('01-Cadastro-Motos'!$I$4:$I$123,MATCH($A5,'01-Cadastro-Motos'!$A$4:$A$123,0)),"")) | D5: =IF($A5="","",IFERROR(INDEX('01-Cadastro-Motos'!$P$4:$P$123,MATCH($A5,'01-Cadastro-Motos'!$A$4:$A$123,0)),"")) | E5: =IF(OR($A5="",$D5=""),"",$C5*'00-Parametros'!$C$13*($D5/30)) | F5: =IF(OR($A5="",$D5=""),"",$C5*'00-Parametros'!$C$14*($D5/30)) | G5: =IF(OR($A5="",$D5="",$D5=0),"",'00-Parametros'!$C$15/$D5)
A6: =IF('01-Cadastro-Motos'!$A6="","",'01-Cadastro-Motos'!$A6) | B6: =IF($A6="","",IFERROR(INDEX('01-Cadastro-Motos'!$B$4:$B$123,MATCH($A6,'01-Cadastro-Motos'!$A$4:$A$123,0)),"")) | C6: =IF($A6="","",IFERROR(INDEX('01-Cadastro-Motos'!$I$4:$I$123,MATCH($A6,'01-Cadastro-Motos'!$A$4:$A$123,0)),"")) | D6: =IF($A6="","",IFERROR(INDEX('01-Cadastro-Motos'!$P$4:$P$123,MATCH($A6,'01-Cadastro-Motos'!$A$4:$A$123,0)),"")) | E6: =IF(OR($A6="",$D6=""),"",$C6*'00-Parametros'!$C$13*($D6/30)) | F6: =IF(OR($A6="",$D6=""),"",$C6*'00-Parametros'!$C$14*($D6/30)) | G6: =IF(OR($A6="",$D6="",$D6=0),"",'00-Parametros'!$C$15/$D6)
A7: =IF('01-Cadastro-Motos'!$A7="","",'01-Cadastro-Motos'!$A7) | B7: =IF($A7="","",IFERROR(INDEX('01-Cadastro-Motos'!$B$4:$B$123,MATCH($A7,'01-Cadastro-Motos'!$A$4:$A$123,0)),"")) | C7: =IF($A7="","",IFERROR(INDEX('01-Cadastro-Motos'!$I$4:$I$123,MATCH($A7,'01-Cadastro-Motos'!$A$4:$A$123,0)),"")) | D7: =IF($A7="","",IFERROR(INDEX('01-Cadastro-Motos'!$P$4:$P$123,MATCH($A7,'01-Cadastro-Motos'!$A$4:$A$123,0)),"")) | E7: =IF(OR($A7="",$D7=""),"",$C7*'00-Parametros'!$C$13*($D7/30)) | F7: =IF(OR($A7="",$D7=""),"",$C7*'00-Parametros'!$C$14*($D7/30)) | G7: =IF(OR($A7="",$D7="",$D7=0),"",'00-Parametros'!$C$15/$D7)
A8: =IF('01-Cadastro-Motos'!$A8="","",'01-Cadastro-Motos'!$A8) | B8: =IF($A8="","",IFERROR(INDEX('01-Cadastro-Motos'!$B$4:$B$123,MATCH($A8,'01-Cadastro-Motos'!$A$4:$A$123,0)),"")) | C8: =IF($A8="","",IFERROR(INDEX('01-Cadastro-Motos'!$I$4:$I$123,MATCH($A8,'01-Cadastro-Motos'!$A$4:$A$123,0)),"")) | D8: =IF($A8="","",IFERROR(INDEX('01-Cadastro-Motos'!$P$4:$P$123,MATCH($A8,'01-Cadastro-Motos'!$A$4:$A$123,0)),"")) | E8: =IF(OR($A8="",$D8=""),"",$C8*'00-Parametros'!$C$13*($D8/30)) | F8: =IF(OR($A8="",$D8=""),"",$C8*'00-Parametros'!$C$14*($D8/30)) | G8: =IF(OR($A8="",$D8="",$D8=0),"",'00-Parametros'!$C$15/$D8)
A9: =IF('01-Cadastro-Motos'!$A9="","",'01-Cadastro-Motos'!$A9) | B9: =IF($A9="","",IFERROR(INDEX('01-Cadastro-Motos'!$B$4:$B$123,MATCH($A9,'01-Cadastro-Motos'!$A$4:$A$123,0)),"")) | C9: =IF($A9="","",IFERROR(INDEX('01-Cadastro-Motos'!$I$4:$I$123,MATCH($A9,'01-Cadastro-Motos'!$A$4:$A$123,0)),"")) | D9: =IF($A9="","",IFERROR(INDEX('01-Cadastro-Motos'!$P$4:$P$123,MATCH($A9,'01-Cadastro-Motos'!$A$4:$A$123,0)),"")) | E9: =IF(OR($A9="",$D9=""),"",$C9*'00-Parametros'!$C$13*($D9/30)) | F9: =IF(OR($A9="",$D9=""),"",$C9*'00-Parametros'!$C$14*($D9/30)) | G9: =IF(OR($A9="",$D9="",$D9=0),"",'00-Parametros'!$C$15/$D9)
A10: =IF('01-Cadastro-Motos'!$A10="","",'01-Cadastro-Motos'!$A10) | B10: =IF($A10="","",IFERROR(INDEX('01-Cadastro-Motos'!$B$4:$B$123,MATCH($A10,'01-Cadastro-Motos'!$A$4:$A$123,0)),"")) | C10: =IF($A10="","",IFERROR(INDEX('01-Cadastro-Motos'!$I$4:$I$123,MATCH($A10,'01-Cadastro-Motos'!$A$4:$A$123,0)),"")) | D10: =IF($A10="","",IFERROR(INDEX('01-Cadastro-Motos'!$P$4:$P$123,MATCH($A10,'01-Cadastro-Motos'!$A$4:$A$123,0)),"")) | E10: =IF(OR($A10="",$D10=""),"",$C10*'00-Parametros'!$C$13*($D10/30)) | F10: =IF(OR($A10="",$D10=""),"",$C10*'00-Parametros'!$C$14*($D10/30)) | G10: =IF(OR($A10="",$D10="",$D10=0),"",'00-Parametros'!$C$15/$D10)
A11: =IF('01-Cadastro-Motos'!$A11="","",'01-Cadastro-Motos'!$A11) | B11: =IF($A11="","",IFERROR(INDEX('01-Cadastro-Motos'!$B$4:$B$123,MATCH($A11,'01-Cadastro-Motos'!$A$4:$A$123,0)),"")) | C11: =IF($A11="","",IFERROR(INDEX('01-Cadastro-Motos'!$I$4:$I$123,MATCH($A11,'01-Cadastro-Motos'!$A$4:$A$123,0)),"")) | D11: =IF($A11="","",IFERROR(INDEX('01-Cadastro-Motos'!$P$4:$P$123,MATCH($A11,'01-Cadastro-Motos'!$A$4:$A$123,0)),"")) | E11: =IF(OR($A11="",$D11=""),"",$C11*'00-Parametros'!$C$13*($D11/30)) | F11: =IF(OR($A11="",$D11=""),"",$C11*'00-Parametros'!$C$14*($D11/30)) | G11: =IF(OR($A11="",$D11="",$D11=0),"",'00-Parametros'!$C$15/$D11)
A12: =IF('01-Cadastro-Motos'!$A12="","",'01-Cadastro-Motos'!$A12) | B12: =IF($A12="","",IFERROR(INDEX('01-Cadastro-Motos'!$B$4:$B$123,MATCH($A12,'01-Cadastro-Motos'!$A$4:$A$123,0)),"")) | C12: =IF($A12="","",IFERROR(INDEX('01-Cadastro-Motos'!$I$4:$I$123,MATCH($A12,'01-Cadastro-Motos'!$A$4:$A$123,0)),"")) | D12: =IF($A12="","",IFERROR(INDEX('01-Cadastro-Motos'!$P$4:$P$123,MATCH($A12,'01-Cadastro-Motos'!$A$4:$A$123,0)),"")) | E12: =IF(OR($A12="",$D12=""),"",$C12*'00-Parametros'!$C$13*($D12/30)) | F12: =IF(OR($A12="",$D12=""),"",$C12*'00-Parametros'!$C$14*($D12/30)) | G12: =IF(OR($A12="",$D12="",$D12=0),"",'00-Parametros'!$C$15/$D12)
A13: =IF('01-Cadastro-Motos'!$A13="","",'01-Cadastro-Motos'!$A13) | B13: =IF($A13="","",IFERROR(INDEX('01-Cadastro-Motos'!$B$4:$B$123,MATCH($A13,'01-Cadastro-Motos'!$A$4:$A$123,0)),"")) | C13: =IF($A13="","",IFERROR(INDEX('01-Cadastro-Motos'!$I$4:$I$123,MATCH($A13,'01-Cadastro-Motos'!$A$4:$A$123,0)),"")) | D13: =IF($A13="","",IFERROR(INDEX('01-Cadastro-Motos'!$P$4:$P$123,MATCH($A13,'01-Cadastro-Motos'!$A$4:$A$123,0)),"")) | E13: =IF(OR($A13="",$D13=""),"",$C13*'00-Parametros'!$C$13*($D13/30)) | F13: =IF(OR($A13="",$D13=""),"",$C13*'00-Parametros'!$C$14*($D13/30)) | G13: =IF(OR($A13="",$D13="",$D13=0),"",'00-Parametros'!$C$15/$D13)
A14: =IF('01-Cadastro-Motos'!$A14="","",'01-Cadastro-Motos'!$A14) | B14: =IF($A14="","",IFERROR(INDEX('01-Cadastro-Motos'!$B$4:$B$123,MATCH($A14,'01-Cadastro-Motos'!$A$4:$A$123,0)),"")) | C14: =IF($A14="","",IFERROR(INDEX('01-Cadastro-Motos'!$I$4:$I$123,MATCH($A14,'01-Cadastro-Motos'!$A$4:$A$123,0)),"")) | D14: =IF($A14="","",IFERROR(INDEX('01-Cadastro-Motos'!$P$4:$P$123,MATCH($A14,'01-Cadastro-Motos'!$A$4:$A$123,0)),"")) | E14: =IF(OR($A14="",$D14=""),"",$C14*'00-Parametros'!$C$13*($D14/30)) | F14: =IF(OR($A14="",$D14=""),"",$C14*'00-Parametros'!$C$14*($D14/30)) | G14: =IF(OR($A14="",$D14="",$D14=0),"",'00-Parametros'!$C$15/$D14)
A15: =IF('01-Cadastro-Motos'!$A15="","",'01-Cadastro-Motos'!$A15) | B15: =IF($A15="","",IFERROR(INDEX('01-Cadastro-Motos'!$B$4:$B$123,MATCH($A15,'01-Cadastro-Motos'!$A$4:$A$123,0)),"")) | C15: =IF($A15="","",IFERROR(INDEX('01-Cadastro-Motos'!$I$4:$I$123,MATCH($A15,'01-Cadastro-Motos'!$A$4:$A$123,0)),"")) | D15: =IF($A15="","",IFERROR(INDEX('01-Cadastro-Motos'!$P$4:$P$123,MATCH($A15,'01-Cadastro-Motos'!$A$4:$A$123,0)),"")) | E15: =IF(OR($A15="",$D15=""),"",$C15*'00-Parametros'!$C$13*($D15/30)) | F15: =IF(OR($A15="",$D15=""),"",$C15*'00-Parametros'!$C$14*($D15/30)) | G15: =IF(OR($A15="",$D15="",$D15=0),"",'00-Parametros'!$C$15/$D15)
... A123: =IF('01-Cadastro-Motos'!$A123="","",'01-Cadastro-Motos'!$A123) | B123: =IF($A123="","",IFERROR(INDEX('01-Cadastro-Motos'!$B$4:$B$123,MATCH($A123,'01-Cadastro-Motos'!$A$4:$A$123,0)),"")) | C123: =IF($A123="","",IFERROR(INDEX('01-Cadastro-Motos'!$I$4:$I$123,MATCH($A123,'01-Cadastro-Motos'!$A$4:$A$123,0)),"")) | D123: =IF($A123="","",IFERROR(INDEX('01-Cadastro-Motos'!$P$4:$P$123,MATCH($A123,'01-Cadastro-Motos'!$A$4:$A$123,0)),"")) | E123: =IF(OR($A123="",$D123=""),"",$C123*'00-Parametros'!$C$13*($D123/30)) | F123: =IF(OR($A123="",$D123=""),"",$C123*'00-Parametros'!$C$14*($D123/30)) | G123: =IF(OR($A123="",$D123="",$D123=0),"",'00-Parametros'!$C$15/$D123)

Sheet 06-Precificacao
A1: Motor de Precificação — Método do Divisor (Pilar 11 do manual)
A3: ID Moto | B3: Modelo (auto) | C3: Valor Compra | D3: Custos Diretos | E3: Custo Financ. Provisionado | F3: Custo Operacional Rateado | G3: CUSTO BASE | H3: Preço Estratégico | I3: Preço Comercial | J3: Preço de Negociação | K3: LP (piso) | L3: ICP (vs. mercado) | M3: Preço Médio Mercado (input p/ ICP)
A4: =IF('01-Cadastro-Motos'!$A4="","",'01-Cadastro-Motos'!$A4) | B4: =IF($A4="","",IFERROR(INDEX('01-Cadastro-Motos'!$B$4:$B$123,MATCH($A4,'01-Cadastro-Motos'!$A$4:$A$123,0)),"")) | C4: =IF($A4="","",IFERROR(INDEX('01-Cadastro-Motos'!$I$4:$I$123,MATCH($A4,'01-Cadastro-Motos'!$A$4:$A$123,0)),"")) | D4: =IF($A4="","",IFERROR(INDEX('02-Custos-Diretos'!$J$4:$J$123,MATCH($A4,'02-Custos-Diretos'!$A$4:$A$123,0)),0)) | E4: =IF($A4="","",$C4*'00-Parametros'!$C$13*('00-Parametros'!$C$15/30)) | F4: =IF($A4="","",'00-Parametros'!$C$16) | G4: =IF($A4="","",SUM(C4:F4)) | H4: =IF($A4="","",$G4/(1-(('00-Parametros'!$C$9+'00-Parametros'!$C$10+'00-Parametros'!$C$11+'00-Parametros'!$C$12)+'00-Parametros'!$C$5))) | I4: =IF($A4="","",$G4/(1-(('00-Parametros'!$C$9+'00-Parametros'!$C$10+'00-Parametros'!$C$11+'00-Parametros'!$C$12)+'00-Parametros'!$C$6))) | J4: =IF($A4="","",$G4/(1-(('00-Parametros'!$C$9+'00-Parametros'!$C$10+'00-Parametros'!$C$11+'00-Parametros'!$C$12)+'00-Parametros'!$C$7))) | K4: =IF($A4="","",$G4/(1-(('00-Parametros'!$C$9+'00-Parametros'!$C$10+'00-Parametros'!$C$11+'00-Parametros'!$C$12)+'00-Parametros'!$C$8))) | L4: =IF(OR($A4="",$M4="",$M4=0),"",$I4/$M4) | M4: 14700
A5: =IF('01-Cadastro-Motos'!$A5="","",'01-Cadastro-Motos'!$A5) | B5: =IF($A5="","",IFERROR(INDEX('01-Cadastro-Motos'!$B$4:$B$123,MATCH($A5,'01-Cadastro-Motos'!$A$4:$A$123,0)),"")) | C5: =IF($A5="","",IFERROR(INDEX('01-Cadastro-Motos'!$I$4:$I$123,MATCH($A5,'01-Cadastro-Motos'!$A$4:$A$123,0)),"")) | D5: =IF($A5="","",IFERROR(INDEX('02-Custos-Diretos'!$J$4:$J$123,MATCH($A5,'02-Custos-Diretos'!$A$4:$A$123,0)),0)) | E5: =IF($A5="","",$C5*'00-Parametros'!$C$13*('00-Parametros'!$C$15/30)) | F5: =IF($A5="","",'00-Parametros'!$C$16) | G5: =IF($A5="","",SUM(C5:F5)) | H5: =IF($A5="","",$G5/(1-(('00-Parametros'!$C$9+'00-Parametros'!$C$10+'00-Parametros'!$C$11+'00-Parametros'!$C$12)+'00-Parametros'!$C$5))) | I5: =IF($A5="","",$G5/(1-(('00-Parametros'!$C$9+'00-Parametros'!$C$10+'00-Parametros'!$C$11+'00-Parametros'!$C$12)+'00-Parametros'!$C$6))) | J5: =IF($A5="","",$G5/(1-(('00-Parametros'!$C$9+'00-Parametros'!$C$10+'00-Parametros'!$C$11+'00-Parametros'!$C$12)+'00-Parametros'!$C$7))) | K5: =IF($A5="","",$G5/(1-(('00-Parametros'!$C$9+'00-Parametros'!$C$10+'00-Parametros'!$C$11+'00-Parametros'!$C$12)+'00-Parametros'!$C$8))) | L5: =IF(OR($A5="",$M5="",$M5=0),"",$I5/$M5)
A6: =IF('01-Cadastro-Motos'!$A6="","",'01-Cadastro-Motos'!$A6) | B6: =IF($A6="","",IFERROR(INDEX('01-Cadastro-Motos'!$B$4:$B$123,MATCH($A6,'01-Cadastro-Motos'!$A$4:$A$123,0)),"")) | C6: =IF($A6="","",IFERROR(INDEX('01-Cadastro-Motos'!$I$4:$I$123,MATCH($A6,'01-Cadastro-Motos'!$A$4:$A$123,0)),"")) | D6: =IF($A6="","",IFERROR(INDEX('02-Custos-Diretos'!$J$4:$J$123,MATCH($A6,'02-Custos-Diretos'!$A$4:$A$123,0)),0)) | E6: =IF($A6="","",$C6*'00-Parametros'!$C$13*('00-Parametros'!$C$15/30)) | F6: =IF($A6="","",'00-Parametros'!$C$16) | G6: =IF($A6="","",SUM(C6:F6)) | H6: =IF($A6="","",$G6/(1-(('00-Parametros'!$C$9+'00-Parametros'!$C$10+'00-Parametros'!$C$11+'00-Parametros'!$C$12)+'00-Parametros'!$C$5))) | I6: =IF($A6="","",$G6/(1-(('00-Parametros'!$C$9+'00-Parametros'!$C$10+'00-Parametros'!$C$11+'00-Parametros'!$C$12)+'00-Parametros'!$C$6))) | J6: =IF($A6="","",$G6/(1-(('00-Parametros'!$C$9+'00-Parametros'!$C$10+'00-Parametros'!$C$11+'00-Parametros'!$C$12)+'00-Parametros'!$C$7))) | K6: =IF($A6="","",$G6/(1-(('00-Parametros'!$C$9+'00-Parametros'!$C$10+'00-Parametros'!$C$11+'00-Parametros'!$C$12)+'00-Parametros'!$C$8))) | L6: =IF(OR($A6="",$M6="",$M6=0),"",$I6/$M6)
A7: =IF('01-Cadastro-Motos'!$A7="","",'01-Cadastro-Motos'!$A7) | B7: =IF($A7="","",IFERROR(INDEX('01-Cadastro-Motos'!$B$4:$B$123,MATCH($A7,'01-Cadastro-Motos'!$A$4:$A$123,0)),"")) | C7: =IF($A7="","",IFERROR(INDEX('01-Cadastro-Motos'!$I$4:$I$123,MATCH($A7,'01-Cadastro-Motos'!$A$4:$A$123,0)),"")) | D7: =IF($A7="","",IFERROR(INDEX('02-Custos-Diretos'!$J$4:$J$123,MATCH($A7,'02-Custos-Diretos'!$A$4:$A$123,0)),0)) | E7: =IF($A7="","",$C7*'00-Parametros'!$C$13*('00-Parametros'!$C$15/30)) | F7: =IF($A7="","",'00-Parametros'!$C$16) | G7: =IF($A7="","",SUM(C7:F7)) | H7: =IF($A7="","",$G7/(1-(('00-Parametros'!$C$9+'00-Parametros'!$C$10+'00-Parametros'!$C$11+'00-Parametros'!$C$12)+'00-Parametros'!$C$5))) | I7: =IF($A7="","",$G7/(1-(('00-Parametros'!$C$9+'00-Parametros'!$C$10+'00-Parametros'!$C$11+'00-Parametros'!$C$12)+'00-Parametros'!$C$6))) | J7: =IF($A7="","",$G7/(1-(('00-Parametros'!$C$9+'00-Parametros'!$C$10+'00-Parametros'!$C$11+'00-Parametros'!$C$12)+'00-Parametros'!$C$7))) | K7: =IF($A7="","",$G7/(1-(('00-Parametros'!$C$9+'00-Parametros'!$C$10+'00-Parametros'!$C$11+'00-Parametros'!$C$12)+'00-Parametros'!$C$8))) | L7: =IF(OR($A7="",$M7="",$M7=0),"",$I7/$M7)
A8: =IF('01-Cadastro-Motos'!$A8="","",'01-Cadastro-Motos'!$A8) | B8: =IF($A8="","",IFERROR(INDEX('01-Cadastro-Motos'!$B$4:$B$123,MATCH($A8,'01-Cadastro-Motos'!$A$4:$A$123,0)),"")) | C8: =IF($A8="","",IFERROR(INDEX('01-Cadastro-Motos'!$I$4:$I$123,MATCH($A8,'01-Cadastro-Motos'!$A$4:$A$123,0)),"")) | D8: =IF($A8="","",IFERROR(INDEX('02-Custos-Diretos'!$J$4:$J$123,MATCH($A8,'02-Custos-Diretos'!$A$4:$A$123,0)),0)) | E8: =IF($A8="","",$C8*'00-Parametros'!$C$13*('00-Parametros'!$C$15/30)) | F8: =IF($A8="","",'00-Parametros'!$C$16) | G8: =IF($A8="","",SUM(C8:F8)) | H8: =IF($A8="","",$G8/(1-(('00-Parametros'!$C$9+'00-Parametros'!$C$10+'00-Parametros'!$C$11+'00-Parametros'!$C$12)+'00-Parametros'!$C$5))) | I8: =IF($A8="","",$G8/(1-(('00-Parametros'!$C$9+'00-Parametros'!$C$10+'00-Parametros'!$C$11+'00-Parametros'!$C$12)+'00-Parametros'!$C$6))) | J8: =IF($A8="","",$G8/(1-(('00-Parametros'!$C$9+'00-Parametros'!$C$10+'00-Parametros'!$C$11+'00-Parametros'!$C$12)+'00-Parametros'!$C$7))) | K8: =IF($A8="","",$G8/(1-(('00-Parametros'!$C$9+'00-Parametros'!$C$10+'00-Parametros'!$C$11+'00-Parametros'!$C$12)+'00-Parametros'!$C$8))) | L8: =IF(OR($A8="",$M8="",$M8=0),"",$I8/$M8)
A9: =IF('01-Cadastro-Motos'!$A9="","",'01-Cadastro-Motos'!$A9) | B9: =IF($A9="","",IFERROR(INDEX('01-Cadastro-Motos'!$B$4:$B$123,MATCH($A9,'01-Cadastro-Motos'!$A$4:$A$123,0)),"")) | C9: =IF($A9="","",IFERROR(INDEX('01-Cadastro-Motos'!$I$4:$I$123,MATCH($A9,'01-Cadastro-Motos'!$A$4:$A$123,0)),"")) | D9: =IF($A9="","",IFERROR(INDEX('02-Custos-Diretos'!$J$4:$J$123,MATCH($A9,'02-Custos-Diretos'!$A$4:$A$123,0)),0)) | E9: =IF($A9="","",$C9*'00-Parametros'!$C$13*('00-Parametros'!$C$15/30)) | F9: =IF($A9="","",'00-Parametros'!$C$16) | G9: =IF($A9="","",SUM(C9:F9)) | H9: =IF($A9="","",$G9/(1-(('00-Parametros'!$C$9+'00-Parametros'!$C$10+'00-Parametros'!$C$11+'00-Parametros'!$C$12)+'00-Parametros'!$C$5))) | I9: =IF($A9="","",$G9/(1-(('00-Parametros'!$C$9+'00-Parametros'!$C$10+'00-Parametros'!$C$11+'00-Parametros'!$C$12)+'00-Parametros'!$C$6))) | J9: =IF($A9="","",$G9/(1-(('00-Parametros'!$C$9+'00-Parametros'!$C$10+'00-Parametros'!$C$11+'00-Parametros'!$C$12)+'00-Parametros'!$C$7))) | K9: =IF($A9="","",$G9/(1-(('00-Parametros'!$C$9+'00-Parametros'!$C$10+'00-Parametros'!$C$11+'00-Parametros'!$C$12)+'00-Parametros'!$C$8))) | L9: =IF(OR($A9="",$M9="",$M9=0),"",$I9/$M9)
A10: =IF('01-Cadastro-Motos'!$A10="","",'01-Cadastro-Motos'!$A10) | B10: =IF($A10="","",IFERROR(INDEX('01-Cadastro-Motos'!$B$4:$B$123,MATCH($A10,'01-Cadastro-Motos'!$A$4:$A$123,0)),"")) | C10: =IF($A10="","",IFERROR(INDEX('01-Cadastro-Motos'!$I$4:$I$123,MATCH($A10,'01-Cadastro-Motos'!$A$4:$A$123,0)),"")) | D10: =IF($A10="","",IFERROR(INDEX('02-Custos-Diretos'!$J$4:$J$123,MATCH($A10,'02-Custos-Diretos'!$A$4:$A$123,0)),0)) | E10: =IF($A10="","",$C10*'00-Parametros'!$C$13*('00-Parametros'!$C$15/30)) | F10: =IF($A10="","",'00-Parametros'!$C$16) | G10: =IF($A10="","",SUM(C10:F10)) | H10: =IF($A10="","",$G10/(1-(('00-Parametros'!$C$9+'00-Parametros'!$C$10+'00-Parametros'!$C$11+'00-Parametros'!$C$12)+'00-Parametros'!$C$5))) | I10: =IF($A10="","",$G10/(1-(('00-Parametros'!$C$9+'00-Parametros'!$C$10+'00-Parametros'!$C$11+'00-Parametros'!$C$12)+'00-Parametros'!$C$6))) | J10: =IF($A10="","",$G10/(1-(('00-Parametros'!$C$9+'00-Parametros'!$C$10+'00-Parametros'!$C$11+'00-Parametros'!$C$12)+'00-Parametros'!$C$7))) | K10: =IF($A10="","",$G10/(1-(('00-Parametros'!$C$9+'00-Parametros'!$C$10+'00-Parametros'!$C$11+'00-Parametros'!$C$12)+'00-Parametros'!$C$8))) | L10: =IF(OR($A10="",$M10="",$M10=0),"",$I10/$M10)
A11: =IF('01-Cadastro-Motos'!$A11="","",'01-Cadastro-Motos'!$A11) | B11: =IF($A11="","",IFERROR(INDEX('01-Cadastro-Motos'!$B$4:$B$123,MATCH($A11,'01-Cadastro-Motos'!$A$4:$A$123,0)),"")) | C11: =IF($A11="","",IFERROR(INDEX('01-Cadastro-Motos'!$I$4:$I$123,MATCH($A11,'01-Cadastro-Motos'!$A$4:$A$123,0)),"")) | D11: =IF($A11="","",IFERROR(INDEX('02-Custos-Diretos'!$J$4:$J$123,MATCH($A11,'02-Custos-Diretos'!$A$4:$A$123,0)),0)) | E11: =IF($A11="","",$C11*'00-Parametros'!$C$13*('00-Parametros'!$C$15/30)) | F11: =IF($A11="","",'00-Parametros'!$C$16) | G11: =IF($A11="","",SUM(C11:F11)) | H11: =IF($A11="","",$G11/(1-(('00-Parametros'!$C$9+'00-Parametros'!$C$10+'00-Parametros'!$C$11+'00-Parametros'!$C$12)+'00-Parametros'!$C$5))) | I11: =IF($A11="","",$G11/(1-(('00-Parametros'!$C$9+'00-Parametros'!$C$10+'00-Parametros'!$C$11+'00-Parametros'!$C$12)+'00-Parametros'!$C$6))) | J11: =IF($A11="","",$G11/(1-(('00-Parametros'!$C$9+'00-Parametros'!$C$10+'00-Parametros'!$C$11+'00-Parametros'!$C$12)+'00-Parametros'!$C$7))) | K11: =IF($A11="","",$G11/(1-(('00-Parametros'!$C$9+'00-Parametros'!$C$10+'00-Parametros'!$C$11+'00-Parametros'!$C$12)+'00-Parametros'!$C$8))) | L11: =IF(OR($A11="",$M11="",$M11=0),"",$I11/$M11)
A12: =IF('01-Cadastro-Motos'!$A12="","",'01-Cadastro-Motos'!$A12) | B12: =IF($A12="","",IFERROR(INDEX('01-Cadastro-Motos'!$B$4:$B$123,MATCH($A12,'01-Cadastro-Motos'!$A$4:$A$123,0)),"")) | C12: =IF($A12="","",IFERROR(INDEX('01-Cadastro-Motos'!$I$4:$I$123,MATCH($A12,'01-Cadastro-Motos'!$A$4:$A$123,0)),"")) | D12: =IF($A12="","",IFERROR(INDEX('02-Custos-Diretos'!$J$4:$J$123,MATCH($A12,'02-Custos-Diretos'!$A$4:$A$123,0)),0)) | E12: =IF($A12="","",$C12*'00-Parametros'!$C$13*('00-Parametros'!$C$15/30)) | F12: =IF($A12="","",'00-Parametros'!$C$16) | G12: =IF($A12="","",SUM(C12:F12)) | H12: =IF($A12="","",$G12/(1-(('00-Parametros'!$C$9+'00-Parametros'!$C$10+'00-Parametros'!$C$11+'00-Parametros'!$C$12)+'00-Parametros'!$C$5))) | I12: =IF($A12="","",$G12/(1-(('00-Parametros'!$C$9+'00-Parametros'!$C$10+'00-Parametros'!$C$11+'00-Parametros'!$C$12)+'00-Parametros'!$C$6))) | J12: =IF($A12="","",$G12/(1-(('00-Parametros'!$C$9+'00-Parametros'!$C$10+'00-Parametros'!$C$11+'00-Parametros'!$C$12)+'00-Parametros'!$C$7))) | K12: =IF($A12="","",$G12/(1-(('00-Parametros'!$C$9+'00-Parametros'!$C$10+'00-Parametros'!$C$11+'00-Parametros'!$C$12)+'00-Parametros'!$C$8))) | L12: =IF(OR($A12="",$M12="",$M12=0),"",$I12/$M12)
A13: =IF('01-Cadastro-Motos'!$A13="","",'01-Cadastro-Motos'!$A13) | B13: =IF($A13="","",IFERROR(INDEX('01-Cadastro-Motos'!$B$4:$B$123,MATCH($A13,'01-Cadastro-Motos'!$A$4:$A$123,0)),"")) | C13: =IF($A13="","",IFERROR(INDEX('01-Cadastro-Motos'!$I$4:$I$123,MATCH($A13,'01-Cadastro-Motos'!$A$4:$A$123,0)),"")) | D13: =IF($A13="","",IFERROR(INDEX('02-Custos-Diretos'!$J$4:$J$123,MATCH($A13,'02-Custos-Diretos'!$A$4:$A$123,0)),0)) | E13: =IF($A13="","",$C13*'00-Parametros'!$C$13*('00-Parametros'!$C$15/30)) | F13: =IF($A13="","",'00-Parametros'!$C$16) | G13: =IF($A13="","",SUM(C13:F13)) | H13: =IF($A13="","",$G13/(1-(('00-Parametros'!$C$9+'00-Parametros'!$C$10+'00-Parametros'!$C$11+'00-Parametros'!$C$12)+'00-Parametros'!$C$5))) | I13: =IF($A13="","",$G13/(1-(('00-Parametros'!$C$9+'00-Parametros'!$C$10+'00-Parametros'!$C$11+'00-Parametros'!$C$12)+'00-Parametros'!$C$6))) | J13: =IF($A13="","",$G13/(1-(('00-Parametros'!$C$9+'00-Parametros'!$C$10+'00-Parametros'!$C$11+'00-Parametros'!$C$12)+'00-Parametros'!$C$7))) | K13: =IF($A13="","",$G13/(1-(('00-Parametros'!$C$9+'00-Parametros'!$C$10+'00-Parametros'!$C$11+'00-Parametros'!$C$12)+'00-Parametros'!$C$8))) | L13: =IF(OR($A13="",$M13="",$M13=0),"",$I13/$M13)
A14: =IF('01-Cadastro-Motos'!$A14="","",'01-Cadastro-Motos'!$A14) | B14: =IF($A14="","",IFERROR(INDEX('01-Cadastro-Motos'!$B$4:$B$123,MATCH($A14,'01-Cadastro-Motos'!$A$4:$A$123,0)),"")) | C14: =IF($A14="","",IFERROR(INDEX('01-Cadastro-Motos'!$I$4:$I$123,MATCH($A14,'01-Cadastro-Motos'!$A$4:$A$123,0)),"")) | D14: =IF($A14="","",IFERROR(INDEX('02-Custos-Diretos'!$J$4:$J$123,MATCH($A14,'02-Custos-Diretos'!$A$4:$A$123,0)),0)) | E14: =IF($A14="","",$C14*'00-Parametros'!$C$13*('00-Parametros'!$C$15/30)) | F14: =IF($A14="","",'00-Parametros'!$C$16) | G14: =IF($A14="","",SUM(C14:F14)) | H14: =IF($A14="","",$G14/(1-(('00-Parametros'!$C$9+'00-Parametros'!$C$10+'00-Parametros'!$C$11+'00-Parametros'!$C$12)+'00-Parametros'!$C$5))) | I14: =IF($A14="","",$G14/(1-(('00-Parametros'!$C$9+'00-Parametros'!$C$10+'00-Parametros'!$C$11+'00-Parametros'!$C$12)+'00-Parametros'!$C$6))) | J14: =IF($A14="","",$G14/(1-(('00-Parametros'!$C$9+'00-Parametros'!$C$10+'00-Parametros'!$C$11+'00-Parametros'!$C$12)+'00-Parametros'!$C$7))) | K14: =IF($A14="","",$G14/(1-(('00-Parametros'!$C$9+'00-Parametros'!$C$10+'00-Parametros'!$C$11+'00-Parametros'!$C$12)+'00-Parametros'!$C$8))) | L14: =IF(OR($A14="",$M14="",$M14=0),"",$I14/$M14)
A15: =IF('01-Cadastro-Motos'!$A15="","",'01-Cadastro-Motos'!$A15) | B15: =IF($A15="","",IFERROR(INDEX('01-Cadastro-Motos'!$B$4:$B$123,MATCH($A15,'01-Cadastro-Motos'!$A$4:$A$123,0)),"")) | C15: =IF($A15="","",IFERROR(INDEX('01-Cadastro-Motos'!$I$4:$I$123,MATCH($A15,'01-Cadastro-Motos'!$A$4:$A$123,0)),"")) | D15: =IF($A15="","",IFERROR(INDEX('02-Custos-Diretos'!$J$4:$J$123,MATCH($A15,'02-Custos-Diretos'!$A$4:$A$123,0)),0)) | E15: =IF($A15="","",$C15*'00-Parametros'!$C$13*('00-Parametros'!$C$15/30)) | F15: =IF($A15="","",'00-Parametros'!$C$16) | G15: =IF($A15="","",SUM(C15:F15)) | H15: =IF($A15="","",$G15/(1-(('00-Parametros'!$C$9+'00-Parametros'!$C$10+'00-Parametros'!$C$11+'00-Parametros'!$C$12)+'00-Parametros'!$C$5))) | I15: =IF($A15="","",$G15/(1-(('00-Parametros'!$C$9+'00-Parametros'!$C$10+'00-Parametros'!$C$11+'00-Parametros'!$C$12)+'00-Parametros'!$C$6))) | J15: =IF($A15="","",$G15/(1-(('00-Parametros'!$C$9+'00-Parametros'!$C$10+'00-Parametros'!$C$11+'00-Parametros'!$C$12)+'00-Parametros'!$C$7))) | K15: =IF($A15="","",$G15/(1-(('00-Parametros'!$C$9+'00-Parametros'!$C$10+'00-Parametros'!$C$11+'00-Parametros'!$C$12)+'00-Parametros'!$C$8))) | L15: =IF(OR($A15="",$M15="",$M15=0),"",$I15/$M15)
A16: =IF('01-Cadastro-Motos'!$A16="","",'01-Cadastro-Motos'!$A16) | B16: =IF($A16="","",IFERROR(INDEX('01-Cadastro-Motos'!$B$4:$B$123,MATCH($A16,'01-Cadastro-Motos'!$A$4:$A$123,0)),"")) | C16: =IF($A16="","",IFERROR(INDEX('01-Cadastro-Motos'!$I$4:$I$123,MATCH($A16,'01-Cadastro-Motos'!$A$4:$A$123,0)),"")) | D16: =IF($A16="","",IFERROR(INDEX('02-Custos-Diretos'!$J$4:$J$123,MATCH($A16,'02-Custos-Diretos'!$A$4:$A$123,0)),0)) | E16: =IF($A16="","",$C16*'00-Parametros'!$C$13*('00-Parametros'!$C$15/30)) | F16: =IF($A16="","",'00-Parametros'!$C$16) | G16: =IF($A16="","",SUM(C16:F16)) | H16: =IF($A16="","",$G16/(1-(('00-Parametros'!$C$9+'00-Parametros'!$C$10+'00-Parametros'!$C$11+'00-Parametros'!$C$12)+'00-Parametros'!$C$5))) | I16: =IF($A16="","",$G16/(1-(('00-Parametros'!$C$9+'00-Parametros'!$C$10+'00-Parametros'!$C$11+'00-Parametros'!$C$12)+'00-Parametros'!$C$6))) | J16: =IF($A16="","",$G16/(1-(('00-Parametros'!$C$9+'00-Parametros'!$C$10+'00-Parametros'!$C$11+'00-Parametros'!$C$12)+'00-Parametros'!$C$7))) | K16: =IF($A16="","",$G16/(1-(('00-Parametros'!$C$9+'00-Parametros'!$C$10+'00-Parametros'!$C$11+'00-Parametros'!$C$12)+'00-Parametros'!$C$8))) | L16: =IF(OR($A16="",$M16="",$M16=0),"",$I16/$M16)
... A123: =IF('01-Cadastro-Motos'!$A123="","",'01-Cadastro-Motos'!$A123) | B123: =IF($A123="","",IFERROR(INDEX('01-Cadastro-Motos'!$B$4:$B$123,MATCH($A123,'01-Cadastro-Motos'!$A$4:$A$123,0)),"")) | C123: =IF($A123="","",IFERROR(INDEX('01-Cadastro-Motos'!$I$4:$I$123,MATCH($A123,'01-Cadastro-Motos'!$A$4:$A$123,0)),"")) | D123: =IF($A123="","",IFERROR(INDEX('02-Custos-Diretos'!$J$4:$J$123,MATCH($A123,'02-Custos-Diretos'!$A$4:$A$123,0)),0)) | E123: =IF($A123="","",$C123*'00-Parametros'!$C$13*('00-Parametros'!$C$15/30)) | F123: =IF($A123="","",'00-Parametros'!$C$16) | G123: =IF($A123="","",SUM(C123:F123)) | H123: =IF($A123="","",$G123/(1-(('00-Parametros'!$C$9+'00-Parametros'!$C$10+'00-Parametros'!$C$11+'00-Parametros'!$C$12)+'00-Parametros'!$C$5))) | I123: =IF($A123="","",$G123/(1-(('00-Parametros'!$C$9+'00-Parametros'!$C$10+'00-Parametros'!$C$11+'00-Parametros'!$C$12)+'00-Parametros'!$C$6))) | J123: =IF($A123="","",$G123/(1-(('00-Parametros'!$C$9+'00-Parametros'!$C$10+'00-Parametros'!$C$11+'00-Parametros'!$C$12)+'00-Parametros'!$C$7))) | K123: =IF($A123="","",$G123/(1-(('00-Parametros'!$C$9+'00-Parametros'!$C$10+'00-Parametros'!$C$11+'00-Parametros'!$C$12)+'00-Parametros'!$C$8))) | L123: =IF(OR($A123="",$M123="",$M123=0),"",$I123/$M123)

Sheet 07-Estoque-Dinamica
A1: Precificação Dinâmica e Saúde do Estoque (Pilares 5 e 10)
A3: ID Moto | B3: Modelo (auto) | C3: Status | D3: Dias em Estoque | E3: Fase do Ciclo | F3: Classificação Saúde | G3: Preço Sugerido Hoje (R$) | H3: Capital Parado (R$) | I3: Revisão Gerencial?
A4: =IF('01-Cadastro-Motos'!$A4="","",'01-Cadastro-Motos'!$A4) | B4: =IF($A4="","",IFERROR(INDEX('01-Cadastro-Motos'!$B$4:$B$123,MATCH($A4,'01-Cadastro-Motos'!$A$4:$A$123,0)),"")) | C4: =IF($A4="","",IFERROR(INDEX('01-Cadastro-Motos'!$K$4:$K$123,MATCH($A4,'01-Cadastro-Motos'!$A$4:$A$123,0)),"")) | D4: =IF($A4="","",IFERROR(INDEX('01-Cadastro-Motos'!$P$4:$P$123,MATCH($A4,'01-Cadastro-Motos'!$A$4:$A$123,0)),"")) | E4: =IF(OR($A4="",$D4=""),"",IF($D4<='00-Parametros'!$C$17,"Fase 1 - Lançamento (0-30)",IF($D4<='00-Parametros'!$C$18,"Fase 2 - Consolidação (31-60)",IF($D4<='00-Parametros'!$C$19,"Fase 3 - Aceleração de Giro (61-90)","Fase 4 - Estoque Envelhecido (>90)")))) | F4: =IF(OR($A4="",$D4=""),"",IF($D4<='00-Parametros'!$C$20,"Estoque Premium",IF($D4<='00-Parametros'!$C$21,"Estoque Saudável",IF($D4<='00-Parametros'!$C$22,"Estoque Atenção","Estoque Crítico")))) | G4: =IF(OR($A4="",$D4=""),"",IF($D4<='00-Parametros'!$C$17,IFERROR(INDEX('06-Precificacao'!$H$4:$H$123,MATCH($A4,'06-Precificacao'!$A$4:$A$123,0)),0),IF($D4<='00-Parametros'!$C$18,IFERROR(INDEX('06-Precificacao'!$I$4:$I$123,MATCH($A4,'06-Precificacao'!$A$4:$A$123,0)),0),IFERROR(INDEX('06-Precificacao'!$J$4:$J$123,MATCH($A4,'06-Precificacao'!$A$4:$A$123,0)),0)))) | H4: =IF(OR($A4="",$C4=""),"",IF($C4<>"Vendida",IFERROR(INDEX('01-Cadastro-Motos'!$I$4:$I$123,MATCH($A4,'01-Cadastro-Motos'!$A$4:$A$123,0)),""),0)) | I4: =IF(OR($A4="",$D4=""),"",IF($D4>'00-Parametros'!$C$19,"SIM - ver Pilar 10.4","Não"))
A5: =IF('01-Cadastro-Motos'!$A5="","",'01-Cadastro-Motos'!$A5) | B5: =IF($A5="","",IFERROR(INDEX('01-Cadastro-Motos'!$B$4:$B$123,MATCH($A5,'01-Cadastro-Motos'!$A$4:$A$123,0)),"")) | C5: =IF($A5="","",IFERROR(INDEX('01-Cadastro-Motos'!$K$4:$K$123,MATCH($A5,'01-Cadastro-Motos'!$A$4:$A$123,0)),"")) | D5: =IF($A5="","",IFERROR(INDEX('01-Cadastro-Motos'!$P$4:$P$123,MATCH($A5,'01-Cadastro-Motos'!$A$4:$A$123,0)),"")) | E5: =IF(OR($A5="",$D5=""),"",IF($D5<='00-Parametros'!$C$17,"Fase 1 - Lançamento (0-30)",IF($D5<='00-Parametros'!$C$18,"Fase 2 - Consolidação (31-60)",IF($D5<='00-Parametros'!$C$19,"Fase 3 - Aceleração de Giro (61-90)","Fase 4 - Estoque Envelhecido (>90)")))) | F5: =IF(OR($A5="",$D5=""),"",IF($D5<='00-Parametros'!$C$20,"Estoque Premium",IF($D5<='00-Parametros'!$C$21,"Estoque Saudável",IF($D5<='00-Parametros'!$C$22,"Estoque Atenção","Estoque Crítico")))) | G5: =IF(OR($A5="",$D5=""),"",IF($D5<='00-Parametros'!$C$17,IFERROR(INDEX('06-Precificacao'!$H$4:$H$123,MATCH($A5,'06-Precificacao'!$A$4:$A$123,0)),0),IF($D5<='00-Parametros'!$C$18,IFERROR(INDEX('06-Precificacao'!$I$4:$I$123,MATCH($A5,'06-Precificacao'!$A$4:$A$123,0)),0),IFERROR(INDEX('06-Precificacao'!$J$4:$J$123,MATCH($A5,'06-Precificacao'!$A$4:$A$123,0)),0)))) | H5: =IF(OR($A5="",$C5=""),"",IF($C5<>"Vendida",IFERROR(INDEX('01-Cadastro-Motos'!$I$4:$I$123,MATCH($A5,'01-Cadastro-Motos'!$A$4:$A$123,0)),""),0)) | I5: =IF(OR($A5="",$D5=""),"",IF($D5>'00-Parametros'!$C$19,"SIM - ver Pilar 10.4","Não"))
A6: =IF('01-Cadastro-Motos'!$A6="","",'01-Cadastro-Motos'!$A6) | B6: =IF($A6="","",IFERROR(INDEX('01-Cadastro-Motos'!$B$4:$B$123,MATCH($A6,'01-Cadastro-Motos'!$A$4:$A$123,0)),"")) | C6: =IF($A6="","",IFERROR(INDEX('01-Cadastro-Motos'!$K$4:$K$123,MATCH($A6,'01-Cadastro-Motos'!$A$4:$A$123,0)),"")) | D6: =IF($A6="","",IFERROR(INDEX('01-Cadastro-Motos'!$P$4:$P$123,MATCH($A6,'01-Cadastro-Motos'!$A$4:$A$123,0)),"")) | E6: =IF(OR($A6="",$D6=""),"",IF($D6<='00-Parametros'!$C$17,"Fase 1 - Lançamento (0-30)",IF($D6<='00-Parametros'!$C$18,"Fase 2 - Consolidação (31-60)",IF($D6<='00-Parametros'!$C$19,"Fase 3 - Aceleração de Giro (61-90)","Fase 4 - Estoque Envelhecido (>90)")))) | F6: =IF(OR($A6="",$D6=""),"",IF($D6<='00-Parametros'!$C$20,"Estoque Premium",IF($D6<='00-Parametros'!$C$21,"Estoque Saudável",IF($D6<='00-Parametros'!$C$22,"Estoque Atenção","Estoque Crítico")))) | G6: =IF(OR($A6="",$D6=""),"",IF($D6<='00-Parametros'!$C$17,IFERROR(INDEX('06-Precificacao'!$H$4:$H$123,MATCH($A6,'06-Precificacao'!$A$4:$A$123,0)),0),IF($D6<='00-Parametros'!$C$18,IFERROR(INDEX('06-Precificacao'!$I$4:$I$123,MATCH($A6,'06-Precificacao'!$A$4:$A$123,0)),0),IFERROR(INDEX('06-Precificacao'!$J$4:$J$123,MATCH($A6,'06-Precificacao'!$A$4:$A$123,0)),0)))) | H6: =IF(OR($A6="",$C6=""),"",IF($C6<>"Vendida",IFERROR(INDEX('01-Cadastro-Motos'!$I$4:$I$123,MATCH($A6,'01-Cadastro-Motos'!$A$4:$A$123,0)),""),0)) | I6: =IF(OR($A6="",$D6=""),"",IF($D6>'00-Parametros'!$C$19,"SIM - ver Pilar 10.4","Não"))
A7: =IF('01-Cadastro-Motos'!$A7="","",'01-Cadastro-Motos'!$A7) | B7: =IF($A7="","",IFERROR(INDEX('01-Cadastro-Motos'!$B$4:$B$123,MATCH($A7,'01-Cadastro-Motos'!$A$4:$A$123,0)),"")) | C7: =IF($A7="","",IFERROR(INDEX('01-Cadastro-Motos'!$K$4:$K$123,MATCH($A7,'01-Cadastro-Motos'!$A$4:$A$123,0)),"")) | D7: =IF($A7="","",IFERROR(INDEX('01-Cadastro-Motos'!$P$4:$P$123,MATCH($A7,'01-Cadastro-Motos'!$A$4:$A$123,0)),"")) | E7: =IF(OR($A7="",$D7=""),"",IF($D7<='00-Parametros'!$C$17,"Fase 1 - Lançamento (0-30)",IF($D7<='00-Parametros'!$C$18,"Fase 2 - Consolidação (31-60)",IF($D7<='00-Parametros'!$C$19,"Fase 3 - Aceleração de Giro (61-90)","Fase 4 - Estoque Envelhecido (>90)")))) | F7: =IF(OR($A7="",$D7=""),"",IF($D7<='00-Parametros'!$C$20,"Estoque Premium",IF($D7<='00-Parametros'!$C$21,"Estoque Saudável",IF($D7<='00-Parametros'!$C$22,"Estoque Atenção","Estoque Crítico")))) | G7: =IF(OR($A7="",$D7=""),"",IF($D7<='00-Parametros'!$C$17,IFERROR(INDEX('06-Precificacao'!$H$4:$H$123,MATCH($A7,'06-Precificacao'!$A$4:$A$123,0)),0),IF($D7<='00-Parametros'!$C$18,IFERROR(INDEX('06-Precificacao'!$I$4:$I$123,MATCH($A7,'06-Precificacao'!$A$4:$A$123,0)),0),IFERROR(INDEX('06-Precificacao'!$J$4:$J$123,MATCH($A7,'06-Precificacao'!$A$4:$A$123,0)),0)))) | H7: =IF(OR($A7="",$C7=""),"",IF($C7<>"Vendida",IFERROR(INDEX('01-Cadastro-Motos'!$I$4:$I$123,MATCH($A7,'01-Cadastro-Motos'!$A$4:$A$123,0)),""),0)) | I7: =IF(OR($A7="",$D7=""),"",IF($D7>'00-Parametros'!$C$19,"SIM - ver Pilar 10.4","Não"))
A8: =IF('01-Cadastro-Motos'!$A8="","",'01-Cadastro-Motos'!$A8) | B8: =IF($A8="","",IFERROR(INDEX('01-Cadastro-Motos'!$B$4:$B$123,MATCH($A8,'01-Cadastro-Motos'!$A$4:$A$123,0)),"")) | C8: =IF($A8="","",IFERROR(INDEX('01-Cadastro-Motos'!$K$4:$K$123,MATCH($A8,'01-Cadastro-Motos'!$A$4:$A$123,0)),"")) | D8: =IF($A8="","",IFERROR(INDEX('01-Cadastro-Motos'!$P$4:$P$123,MATCH($A8,'01-Cadastro-Motos'!$A$4:$A$123,0)),"")) | E8: =IF(OR($A8="",$D8=""),"",IF($D8<='00-Parametros'!$C$17,"Fase 1 - Lançamento (0-30)",IF($D8<='00-Parametros'!$C$18,"Fase 2 - Consolidação (31-60)",IF($D8<='00-Parametros'!$C$19,"Fase 3 - Aceleração de Giro (61-90)","Fase 4 - Estoque Envelhecido (>90)")))) | F8: =IF(OR($A8="",$D8=""),"",IF($D8<='00-Parametros'!$C$20,"Estoque Premium",IF($D8<='00-Parametros'!$C$21,"Estoque Saudável",IF($D8<='00-Parametros'!$C$22,"Estoque Atenção","Estoque Crítico")))) | G8: =IF(OR($A8="",$D8=""),"",IF($D8<='00-Parametros'!$C$17,IFERROR(INDEX('06-Precificacao'!$H$4:$H$123,MATCH($A8,'06-Precificacao'!$A$4:$A$123,0)),0),IF($D8<='00-Parametros'!$C$18,IFERROR(INDEX('06-Precificacao'!$I$4:$I$123,MATCH($A8,'06-Precificacao'!$A$4:$A$123,0)),0),IFERROR(INDEX('06-Precificacao'!$J$4:$J$123,MATCH($A8,'06-Precificacao'!$A$4:$A$123,0)),0)))) | H8: =IF(OR($A8="",$C8=""),"",IF($C8<>"Vendida",IFERROR(INDEX('01-Cadastro-Motos'!$I$4:$I$123,MATCH($A8,'01-Cadastro-Motos'!$A$4:$A$123,0)),""),0)) | I8: =IF(OR($A8="",$D8=""),"",IF($D8>'00-Parametros'!$C$19,"SIM - ver Pilar 10.4","Não"))
A9: =IF('01-Cadastro-Motos'!$A9="","",'01-Cadastro-Motos'!$A9) | B9: =IF($A9="","",IFERROR(INDEX('01-Cadastro-Motos'!$B$4:$B$123,MATCH($A9,'01-Cadastro-Motos'!$A$4:$A$123,0)),"")) | C9: =IF($A9="","",IFERROR(INDEX('01-Cadastro-Motos'!$K$4:$K$123,MATCH($A9,'01-Cadastro-Motos'!$A$4:$A$123,0)),"")) | D9: =IF($A9="","",IFERROR(INDEX('01-Cadastro-Motos'!$P$4:$P$123,MATCH($A9,'01-Cadastro-Motos'!$A$4:$A$123,0)),"")) | E9: =IF(OR($A9="",$D9=""),"",IF($D9<='00-Parametros'!$C$17,"Fase 1 - Lançamento (0-30)",IF($D9<='00-Parametros'!$C$18,"Fase 2 - Consolidação (31-60)",IF($D9<='00-Parametros'!$C$19,"Fase 3 - Aceleração de Giro (61-90)","Fase 4 - Estoque Envelhecido (>90)")))) | F9: =IF(OR($A9="",$D9=""),"",IF($D9<='00-Parametros'!$C$20,"Estoque Premium",IF($D9<='00-Parametros'!$C$21,"Estoque Saudável",IF($D9<='00-Parametros'!$C$22,"Estoque Atenção","Estoque Crítico")))) | G9: =IF(OR($A9="",$D9=""),"",IF($D9<='00-Parametros'!$C$17,IFERROR(INDEX('06-Precificacao'!$H$4:$H$123,MATCH($A9,'06-Precificacao'!$A$4:$A$123,0)),0),IF($D9<='00-Parametros'!$C$18,IFERROR(INDEX('06-Precificacao'!$I$4:$I$123,MATCH($A9,'06-Precificacao'!$A$4:$A$123,0)),0),IFERROR(INDEX('06-Precificacao'!$J$4:$J$123,MATCH($A9,'06-Precificacao'!$A$4:$A$123,0)),0)))) | H9: =IF(OR($A9="",$C9=""),"",IF($C9<>"Vendida",IFERROR(INDEX('01-Cadastro-Motos'!$I$4:$I$123,MATCH($A9,'01-Cadastro-Motos'!$A$4:$A$123,0)),""),0)) | I9: =IF(OR($A9="",$D9=""),"",IF($D9>'00-Parametros'!$C$19,"SIM - ver Pilar 10.4","Não"))
A10: =IF('01-Cadastro-Motos'!$A10="","",'01-Cadastro-Motos'!$A10) | B10: =IF($A10="","",IFERROR(INDEX('01-Cadastro-Motos'!$B$4:$B$123,MATCH($A10,'01-Cadastro-Motos'!$A$4:$A$123,0)),"")) | C10: =IF($A10="","",IFERROR(INDEX('01-Cadastro-Motos'!$K$4:$K$123,MATCH($A10,'01-Cadastro-Motos'!$A$4:$A$123,0)),"")) | D10: =IF($A10="","",IFERROR(INDEX('01-Cadastro-Motos'!$P$4:$P$123,MATCH($A10,'01-Cadastro-Motos'!$A$4:$A$123,0)),"")) | E10: =IF(OR($A10="",$D10=""),"",IF($D10<='00-Parametros'!$C$17,"Fase 1 - Lançamento (0-30)",IF($D10<='00-Parametros'!$C$18,"Fase 2 - Consolidação (31-60)",IF($D10<='00-Parametros'!$C$19,"Fase 3 - Aceleração de Giro (61-90)","Fase 4 - Estoque Envelhecido (>90)")))) | F10: =IF(OR($A10="",$D10=""),"",IF($D10<='00-Parametros'!$C$20,"Estoque Premium",IF($D10<='00-Parametros'!$C$21,"Estoque Saudável",IF($D10<='00-Parametros'!$C$22,"Estoque Atenção","Estoque Crítico")))) | G10: =IF(OR($A10="",$D10=""),"",IF($D10<='00-Parametros'!$C$17,IFERROR(INDEX('06-Precificacao'!$H$4:$H$123,MATCH($A10,'06-Precificacao'!$A$4:$A$123,0)),0),IF($D10<='00-Parametros'!$C$18,IFERROR(INDEX('06-Precificacao'!$I$4:$I$123,MATCH($A10,'06-Precificacao'!$A$4:$A$123,0)),0),IFERROR(INDEX('06-Precificacao'!$J$4:$J$123,MATCH($A10,'06-Precificacao'!$A$4:$A$123,0)),0)))) | H10: =IF(OR($A10="",$C10=""),"",IF($C10<>"Vendida",IFERROR(INDEX('01-Cadastro-Motos'!$I$4:$I$123,MATCH($A10,'01-Cadastro-Motos'!$A$4:$A$123,0)),""),0)) | I10: =IF(OR($A10="",$D10=""),"",IF($D10>'00-Parametros'!$C$19,"SIM - ver Pilar 10.4","Não"))
A11: =IF('01-Cadastro-Motos'!$A11="","",'01-Cadastro-Motos'!$A11) | B11: =IF($A11="","",IFERROR(INDEX('01-Cadastro-Motos'!$B$4:$B$123,MATCH($A11,'01-Cadastro-Motos'!$A$4:$A$123,0)),"")) | C11: =IF($A11="","",IFERROR(INDEX('01-Cadastro-Motos'!$K$4:$K$123,MATCH($A11,'01-Cadastro-Motos'!$A$4:$A$123,0)),"")) | D11: =IF($A11="","",IFERROR(INDEX('01-Cadastro-Motos'!$P$4:$P$123,MATCH($A11,'01-Cadastro-Motos'!$A$4:$A$123,0)),"")) | E11: =IF(OR($A11="",$D11=""),"",IF($D11<='00-Parametros'!$C$17,"Fase 1 - Lançamento (0-30)",IF($D11<='00-Parametros'!$C$18,"Fase 2 - Consolidação (31-60)",IF($D11<='00-Parametros'!$C$19,"Fase 3 - Aceleração de Giro (61-90)","Fase 4 - Estoque Envelhecido (>90)")))) | F11: =IF(OR($A11="",$D11=""),"",IF($D11<='00-Parametros'!$C$20,"Estoque Premium",IF($D11<='00-Parametros'!$C$21,"Estoque Saudável",IF($D11<='00-Parametros'!$C$22,"Estoque Atenção","Estoque Crítico")))) | G11: =IF(OR($A11="",$D11=""),"",IF($D11<='00-Parametros'!$C$17,IFERROR(INDEX('06-Precificacao'!$H$4:$H$123,MATCH($A11,'06-Precificacao'!$A$4:$A$123,0)),0),IF($D11<='00-Parametros'!$C$18,IFERROR(INDEX('06-Precificacao'!$I$4:$I$123,MATCH($A11,'06-Precificacao'!$A$4:$A$123,0)),0),IFERROR(INDEX('06-Precificacao'!$J$4:$J$123,MATCH($A11,'06-Precificacao'!$A$4:$A$123,0)),0)))) | H11: =IF(OR($A11="",$C11=""),"",IF($C11<>"Vendida",IFERROR(INDEX('01-Cadastro-Motos'!$I$4:$I$123,MATCH($A11,'01-Cadastro-Motos'!$A$4:$A$123,0)),""),0)) | I11: =IF(OR($A11="",$D11=""),"",IF($D11>'00-Parametros'!$C$19,"SIM - ver Pilar 10.4","Não"))
A12: =IF('01-Cadastro-Motos'!$A12="","",'01-Cadastro-Motos'!$A12) | B12: =IF($A12="","",IFERROR(INDEX('01-Cadastro-Motos'!$B$4:$B$123,MATCH($A12,'01-Cadastro-Motos'!$A$4:$A$123,0)),"")) | C12: =IF($A12="","",IFERROR(INDEX('01-Cadastro-Motos'!$K$4:$K$123,MATCH($A12,'01-Cadastro-Motos'!$A$4:$A$123,0)),"")) | D12: =IF($A12="","",IFERROR(INDEX('01-Cadastro-Motos'!$P$4:$P$123,MATCH($A12,'01-Cadastro-Motos'!$A$4:$A$123,0)),"")) | E12: =IF(OR($A12="",$D12=""),"",IF($D12<='00-Parametros'!$C$17,"Fase 1 - Lançamento (0-30)",IF($D12<='00-Parametros'!$C$18,"Fase 2 - Consolidação (31-60)",IF($D12<='00-Parametros'!$C$19,"Fase 3 - Aceleração de Giro (61-90)","Fase 4 - Estoque Envelhecido (>90)")))) | F12: =IF(OR($A12="",$D12=""),"",IF($D12<='00-Parametros'!$C$20,"Estoque Premium",IF($D12<='00-Parametros'!$C$21,"Estoque Saudável",IF($D12<='00-Parametros'!$C$22,"Estoque Atenção","Estoque Crítico")))) | G12: =IF(OR($A12="",$D12=""),"",IF($D12<='00-Parametros'!$C$17,IFERROR(INDEX('06-Precificacao'!$H$4:$H$123,MATCH($A12,'06-Precificacao'!$A$4:$A$123,0)),0),IF($D12<='00-Parametros'!$C$18,IFERROR(INDEX('06-Precificacao'!$I$4:$I$123,MATCH($A12,'06-Precificacao'!$A$4:$A$123,0)),0),IFERROR(INDEX('06-Precificacao'!$J$4:$J$123,MATCH($A12,'06-Precificacao'!$A$4:$A$123,0)),0)))) | H12: =IF(OR($A12="",$C12=""),"",IF($C12<>"Vendida",IFERROR(INDEX('01-Cadastro-Motos'!$I$4:$I$123,MATCH($A12,'01-Cadastro-Motos'!$A$4:$A$123,0)),""),0)) | I12: =IF(OR($A12="",$D12=""),"",IF($D12>'00-Parametros'!$C$19,"SIM - ver Pilar 10.4","Não"))
A13: =IF('01-Cadastro-Motos'!$A13="","",'01-Cadastro-Motos'!$A13) | B13: =IF($A13="","",IFERROR(INDEX('01-Cadastro-Motos'!$B$4:$B$123,MATCH($A13,'01-Cadastro-Motos'!$A$4:$A$123,0)),"")) | C13: =IF($A13="","",IFERROR(INDEX('01-Cadastro-Motos'!$K$4:$K$123,MATCH($A13,'01-Cadastro-Motos'!$A$4:$A$123,0)),"")) | D13: =IF($A13="","",IFERROR(INDEX('01-Cadastro-Motos'!$P$4:$P$123,MATCH($A13,'01-Cadastro-Motos'!$A$4:$A$123,0)),"")) | E13: =IF(OR($A13="",$D13=""),"",IF($D13<='00-Parametros'!$C$17,"Fase 1 - Lançamento (0-30)",IF($D13<='00-Parametros'!$C$18,"Fase 2 - Consolidação (31-60)",IF($D13<='00-Parametros'!$C$19,"Fase 3 - Aceleração de Giro (61-90)","Fase 4 - Estoque Envelhecido (>90)")))) | F13: =IF(OR($A13="",$D13=""),"",IF($D13<='00-Parametros'!$C$20,"Estoque Premium",IF($D13<='00-Parametros'!$C$21,"Estoque Saudável",IF($D13<='00-Parametros'!$C$22,"Estoque Atenção","Estoque Crítico")))) | G13: =IF(OR($A13="",$D13=""),"",IF($D13<='00-Parametros'!$C$17,IFERROR(INDEX('06-Precificacao'!$H$4:$H$123,MATCH($A13,'06-Precificacao'!$A$4:$A$123,0)),0),IF($D13<='00-Parametros'!$C$18,IFERROR(INDEX('06-Precificacao'!$I$4:$I$123,MATCH($A13,'06-Precificacao'!$A$4:$A$123,0)),0),IFERROR(INDEX('06-Precificacao'!$J$4:$J$123,MATCH($A13,'06-Precificacao'!$A$4:$A$123,0)),0)))) | H13: =IF(OR($A13="",$C13=""),"",IF($C13<>"Vendida",IFERROR(INDEX('01-Cadastro-Motos'!$I$4:$I$123,MATCH($A13,'01-Cadastro-Motos'!$A$4:$A$123,0)),""),0)) | I13: =IF(OR($A13="",$D13=""),"",IF($D13>'00-Parametros'!$C$19,"SIM - ver Pilar 10.4","Não"))
A14: =IF('01-Cadastro-Motos'!$A14="","",'01-Cadastro-Motos'!$A14) | B14: =IF($A14="","",IFERROR(INDEX('01-Cadastro-Motos'!$B$4:$B$123,MATCH($A14,'01-Cadastro-Motos'!$A$4:$A$123,0)),"")) | C14: =IF($A14="","",IFERROR(INDEX('01-Cadastro-Motos'!$K$4:$K$123,MATCH($A14,'01-Cadastro-Motos'!$A$4:$A$123,0)),"")) | D14: =IF($A14="","",IFERROR(INDEX('01-Cadastro-Motos'!$P$4:$P$123,MATCH($A14,'01-Cadastro-Motos'!$A$4:$A$123,0)),"")) | E14: =IF(OR($A14="",$D14=""),"",IF($D14<='00-Parametros'!$C$17,"Fase 1 - Lançamento (0-30)",IF($D14<='00-Parametros'!$C$18,"Fase 2 - Consolidação (31-60)",IF($D14<='00-Parametros'!$C$19,"Fase 3 - Aceleração de Giro (61-90)","Fase 4 - Estoque Envelhecido (>90)")))) | F14: =IF(OR($A14="",$D14=""),"",IF($D14<='00-Parametros'!$C$20,"Estoque Premium",IF($D14<='00-Parametros'!$C$21,"Estoque Saudável",IF($D14<='00-Parametros'!$C$22,"Estoque Atenção","Estoque Crítico")))) | G14: =IF(OR($A14="",$D14=""),"",IF($D14<='00-Parametros'!$C$17,IFERROR(INDEX('06-Precificacao'!$H$4:$H$123,MATCH($A14,'06-Precificacao'!$A$4:$A$123,0)),0),IF($D14<='00-Parametros'!$C$18,IFERROR(INDEX('06-Precificacao'!$I$4:$I$123,MATCH($A14,'06-Precificacao'!$A$4:$A$123,0)),0),IFERROR(INDEX('06-Precificacao'!$J$4:$J$123,MATCH($A14,'06-Precificacao'!$A$4:$A$123,0)),0)))) | H14: =IF(OR($A14="",$C14=""),"",IF($C14<>"Vendida",IFERROR(INDEX('01-Cadastro-Motos'!$I$4:$I$123,MATCH($A14,'01-Cadastro-Motos'!$A$4:$A$123,0)),""),0)) | I14: =IF(OR($A14="",$D14=""),"",IF($D14>'00-Parametros'!$C$19,"SIM - ver Pilar 10.4","Não"))
A15: =IF('01-Cadastro-Motos'!$A15="","",'01-Cadastro-Motos'!$A15) | B15: =IF($A15="","",IFERROR(INDEX('01-Cadastro-Motos'!$B$4:$B$123,MATCH($A15,'01-Cadastro-Motos'!$A$4:$A$123,0)),"")) | C15: =IF($A15="","",IFERROR(INDEX('01-Cadastro-Motos'!$K$4:$K$123,MATCH($A15,'01-Cadastro-Motos'!$A$4:$A$123,0)),"")) | D15: =IF($A15="","",IFERROR(INDEX('01-Cadastro-Motos'!$P$4:$P$123,MATCH($A15,'01-Cadastro-Motos'!$A$4:$A$123,0)),"")) | E15: =IF(OR($A15="",$D15=""),"",IF($D15<='00-Parametros'!$C$17,"Fase 1 - Lançamento (0-30)",IF($D15<='00-Parametros'!$C$18,"Fase 2 - Consolidação (31-60)",IF($D15<='00-Parametros'!$C$19,"Fase 3 - Aceleração de Giro (61-90)","Fase 4 - Estoque Envelhecido (>90)")))) | F15: =IF(OR($A15="",$D15=""),"",IF($D15<='00-Parametros'!$C$20,"Estoque Premium",IF($D15<='00-Parametros'!$C$21,"Estoque Saudável",IF($D15<='00-Parametros'!$C$22,"Estoque Atenção","Estoque Crítico")))) | G15: =IF(OR($A15="",$D15=""),"",IF($D15<='00-Parametros'!$C$17,IFERROR(INDEX('06-Precificacao'!$H$4:$H$123,MATCH($A15,'06-Precificacao'!$A$4:$A$123,0)),0),IF($D15<='00-Parametros'!$C$18,IFERROR(INDEX('06-Precificacao'!$I$4:$I$123,MATCH($A15,'06-Precificacao'!$A$4:$A$123,0)),0),IFERROR(INDEX('06-Precificacao'!$J$4:$J$123,MATCH($A15,'06-Precificacao'!$A$4:$A$123,0)),0)))) | H15: =IF(OR($A15="",$C15=""),"",IF($C15<>"Vendida",IFERROR(INDEX('01-Cadastro-Motos'!$I$4:$I$123,MATCH($A15,'01-Cadastro-Motos'!$A$4:$A$123,0)),""),0)) | I15: =IF(OR($A15="",$D15=""),"",IF($D15>'00-Parametros'!$C$19,"SIM - ver Pilar 10.4","Não"))
... A123: =IF('01-Cadastro-Motos'!$A123="","",'01-Cadastro-Motos'!$A123) | B123: =IF($A123="","",IFERROR(INDEX('01-Cadastro-Motos'!$B$4:$B$123,MATCH($A123,'01-Cadastro-Motos'!$A$4:$A$123,0)),"")) | C123: =IF($A123="","",IFERROR(INDEX('01-Cadastro-Motos'!$K$4:$K$123,MATCH($A123,'01-Cadastro-Motos'!$A$4:$A$123,0)),"")) | D123: =IF($A123="","",IFERROR(INDEX('01-Cadastro-Motos'!$P$4:$P$123,MATCH($A123,'01-Cadastro-Motos'!$A$4:$A$123,0)),"")) | E123: =IF(OR($A123="",$D123=""),"",IF($D123<='00-Parametros'!$C$17,"Fase 1 - Lançamento (0-30)",IF($D123<='00-Parametros'!$C$18,"Fase 2 - Consolidação (31-60)",IF($D123<='00-Parametros'!$C$19,"Fase 3 - Aceleração de Giro (61-90)","Fase 4 - Estoque Envelhecido (>90)")))) | F123: =IF(OR($A123="",$D123=""),"",IF($D123<='00-Parametros'!$C$20,"Estoque Premium",IF($D123<='00-Parametros'!$C$21,"Estoque Saudável",IF($D123<='00-Parametros'!$C$22,"Estoque Atenção","Estoque Crítico")))) | G123: =IF(OR($A123="",$D123=""),"",IF($D123<='00-Parametros'!$C$17,IFERROR(INDEX('06-Precificacao'!$H$4:$H$123,MATCH($A123,'06-Precificacao'!$A$4:$A$123,0)),0),IF($D123<='00-Parametros'!$C$18,IFERROR(INDEX('06-Precificacao'!$I$4:$I$123,MATCH($A123,'06-Precificacao'!$A$4:$A$123,0)),0),IFERROR(INDEX('06-Precificacao'!$J$4:$J$123,MATCH($A123,'06-Precificacao'!$A$4:$A$123,0)),0)))) | H123: =IF(OR($A123="",$C123=""),"",IF($C123<>"Vendida",IFERROR(INDEX('01-Cadastro-Motos'!$I$4:$I$123,MATCH($A123,'01-Cadastro-Motos'!$A$4:$A$123,0)),""),0)) | I123: =IF(OR($A123="",$D123=""),"",IF($D123>'00-Parametros'!$C$19,"SIM - ver Pilar 10.4","Não"))

Sheet 08-Vendas-Negociacao
A1: Registro de Vendas e Negociação (Pilares 6 e 7)
A3: ID Moto | B3: Modelo (auto) | C3: ID Vendedor | D3: Data Venda | E3: Preço Comercial (auto) | F3: LP (auto) | G3: Preço Vendido (R$) | H3: Desconto (R$) | I3: Desconto (%) | J3: Abaixo do LP? | K3: Lucro Líquido Real (R$) | L3: Margem Líquida Realizada (%)
A4: MOTO-002 | B4: =IF($A4="","",IFERROR(INDEX('01-Cadastro-Motos'!$B$4:$B$123,MATCH($A4,'01-Cadastro-Motos'!$A$4:$A$123,0)),"")) | C4: VEND-02 | D4: 46187 | E4: =IF($A4="","",IFERROR(INDEX('06-Precificacao'!$I$4:$I$123,MATCH($A4,'06-Precificacao'!$A$4:$A$123,0)),0)) | F4: =IF($A4="","",IFERROR(INDEX('06-Precificacao'!$K$4:$K$123,MATCH($A4,'06-Precificacao'!$A$4:$A$123,0)),0)) | G4: 16000 | H4: =IF(OR($A4="",$G4=""),"",$E4-$G4) | I4: =IF(OR($A4="",$G4="",$E4=0),"",$H4/$E4) | J4: =IF(OR($A4="",$G4=""),"",IF($G4<$F4,"SIM - abaixo do LP","Não")) | K4: =IF(OR($A4="",$G4=""),"",$G4-(IFERROR(INDEX('06-Precificacao'!$G$4:$G$123,MATCH($A4,'06-Precificacao'!$A$4:$A$123,0)),0)-IFERROR(INDEX('06-Precificacao'!$E$4:$E$123,MATCH($A4,'06-Precificacao'!$A$4:$A$123,0)),0)+IFERROR(INDEX('05-Financeiro'!$E$4:$E$123,MATCH($A4,'05-Financeiro'!$A$4:$A$123,0)),0))-($G4*'00-Parametros'!$C$9)-($G4*'00-Parametros'!$C$10)-IFERROR(INDEX('03-Marketing'!$C$4:$C$123,MATCH($A4,'03-Marketing'!$A$4:$A$123,0)),0)-($G4*'00-Parametros'!$C$12)) | L4: =IF(OR($A4="",$G4="",$G4=0),"",$K4/$G4)
B5: =IF($A5="","",IFERROR(INDEX('01-Cadastro-Motos'!$B$4:$B$123,MATCH($A5,'01-Cadastro-Motos'!$A$4:$A$123,0)),"")) | E5: =IF($A5="","",IFERROR(INDEX('06-Precificacao'!$I$4:$I$123,MATCH($A5,'06-Precificacao'!$A$4:$A$123,0)),0)) | F5: =IF($A5="","",IFERROR(INDEX('06-Precificacao'!$K$4:$K$123,MATCH($A5,'06-Precificacao'!$A$4:$A$123,0)),0)) | H5: =IF(OR($A5="",$G5=""),"",$E5-$G5) | I5: =IF(OR($A5="",$G5="",$E5=0),"",$H5/$E5) | J5: =IF(OR($A5="",$G5=""),"",IF($G5<$F5,"SIM - abaixo do LP","Não")) | K5: =IF(OR($A5="",$G5=""),"",$G5-(IFERROR(INDEX('06-Precificacao'!$G$4:$G$123,MATCH($A5,'06-Precificacao'!$A$4:$A$123,0)),0)-IFERROR(INDEX('06-Precificacao'!$E$4:$E$123,MATCH($A5,'06-Precificacao'!$A$4:$A$123,0)),0)+IFERROR(INDEX('05-Financeiro'!$E$4:$E$123,MATCH($A5,'05-Financeiro'!$A$4:$A$123,0)),0))-($G5*'00-Parametros'!$C$9)-($G5*'00-Parametros'!$C$10)-IFERROR(INDEX('03-Marketing'!$C$4:$C$123,MATCH($A5,'03-Marketing'!$A$4:$A$123,0)),0)-($G5*'00-Parametros'!$C$12)) | L5: =IF(OR($A5="",$G5="",$G5=0),"",$K5/$G5)
B6: =IF($A6="","",IFERROR(INDEX('01-Cadastro-Motos'!$B$4:$B$123,MATCH($A6,'01-Cadastro-Motos'!$A$4:$A$123,0)),"")) | E6: =IF($A6="","",IFERROR(INDEX('06-Precificacao'!$I$4:$I$123,MATCH($A6,'06-Precificacao'!$A$4:$A$123,0)),0)) | F6: =IF($A6="","",IFERROR(INDEX('06-Precificacao'!$K$4:$K$123,MATCH($A6,'06-Precificacao'!$A$4:$A$123,0)),0)) | H6: =IF(OR($A6="",$G6=""),"",$E6-$G6) | I6: =IF(OR($A6="",$G6="",$E6=0),"",$H6/$E6) | J6: =IF(OR($A6="",$G6=""),"",IF($G6<$F6,"SIM - abaixo do LP","Não")) | K6: =IF(OR($A6="",$G6=""),"",$G6-(IFERROR(INDEX('06-Precificacao'!$G$4:$G$123,MATCH($A6,'06-Precificacao'!$A$4:$A$123,0)),0)-IFERROR(INDEX('06-Precificacao'!$E$4:$E$123,MATCH($A6,'06-Precificacao'!$A$4:$A$123,0)),0)+IFERROR(INDEX('05-Financeiro'!$E$4:$E$123,MATCH($A6,'05-Financeiro'!$A$4:$A$123,0)),0))-($G6*'00-Parametros'!$C$9)-($G6*'00-Parametros'!$C$10)-IFERROR(INDEX('03-Marketing'!$C$4:$C$123,MATCH($A6,'03-Marketing'!$A$4:$A$123,0)),0)-($G6*'00-Parametros'!$C$12)) | L6: =IF(OR($A6="",$G6="",$G6=0),"",$K6/$G6)
B7: =IF($A7="","",IFERROR(INDEX('01-Cadastro-Motos'!$B$4:$B$123,MATCH($A7,'01-Cadastro-Motos'!$A$4:$A$123,0)),"")) | E7: =IF($A7="","",IFERROR(INDEX('06-Precificacao'!$I$4:$I$123,MATCH($A7,'06-Precificacao'!$A$4:$A$123,0)),0)) | F7: =IF($A7="","",IFERROR(INDEX('06-Precificacao'!$K$4:$K$123,MATCH($A7,'06-Precificacao'!$A$4:$A$123,0)),0)) | H7: =IF(OR($A7="",$G7=""),"",$E7-$G7) | I7: =IF(OR($A7="",$G7="",$E7=0),"",$H7/$E7) | J7: =IF(OR($A7="",$G7=""),"",IF($G7<$F7,"SIM - abaixo do LP","Não")) | K7: =IF(OR($A7="",$G7=""),"",$G7-(IFERROR(INDEX('06-Precificacao'!$G$4:$G$123,MATCH($A7,'06-Precificacao'!$A$4:$A$123,0)),0)-IFERROR(INDEX('06-Precificacao'!$E$4:$E$123,MATCH($A7,'06-Precificacao'!$A$4:$A$123,0)),0)+IFERROR(INDEX('05-Financeiro'!$E$4:$E$123,MATCH($A7,'05-Financeiro'!$A$4:$A$123,0)),0))-($G7*'00-Parametros'!$C$9)-($G7*'00-Parametros'!$C$10)-IFERROR(INDEX('03-Marketing'!$C$4:$C$123,MATCH($A7,'03-Marketing'!$A$4:$A$123,0)),0)-($G7*'00-Parametros'!$C$12)) | L7: =IF(OR($A7="",$G7="",$G7=0),"",$K7/$G7)
B8: =IF($A8="","",IFERROR(INDEX('01-Cadastro-Motos'!$B$4:$B$123,MATCH($A8,'01-Cadastro-Motos'!$A$4:$A$123,0)),"")) | E8: =IF($A8="","",IFERROR(INDEX('06-Precificacao'!$I$4:$I$123,MATCH($A8,'06-Precificacao'!$A$4:$A$123,0)),0)) | F8: =IF($A8="","",IFERROR(INDEX('06-Precificacao'!$K$4:$K$123,MATCH($A8,'06-Precificacao'!$A$4:$A$123,0)),0)) | H8: =IF(OR($A8="",$G8=""),"",$E8-$G8) | I8: =IF(OR($A8="",$G8="",$E8=0),"",$H8/$E8) | J8: =IF(OR($A8="",$G8=""),"",IF($G8<$F8,"SIM - abaixo do LP","Não")) | K8: =IF(OR($A8="",$G8=""),"",$G8-(IFERROR(INDEX('06-Precificacao'!$G$4:$G$123,MATCH($A8,'06-Precificacao'!$A$4:$A$123,0)),0)-IFERROR(INDEX('06-Precificacao'!$E$4:$E$123,MATCH($A8,'06-Precificacao'!$A$4:$A$123,0)),0)+IFERROR(INDEX('05-Financeiro'!$E$4:$E$123,MATCH($A8,'05-Financeiro'!$A$4:$A$123,0)),0))-($G8*'00-Parametros'!$C$9)-($G8*'00-Parametros'!$C$10)-IFERROR(INDEX('03-Marketing'!$C$4:$C$123,MATCH($A8,'03-Marketing'!$A$4:$A$123,0)),0)-($G8*'00-Parametros'!$C$12)) | L8: =IF(OR($A8="",$G8="",$G8=0),"",$K8/$G8)
B9: =IF($A9="","",IFERROR(INDEX('01-Cadastro-Motos'!$B$4:$B$123,MATCH($A9,'01-Cadastro-Motos'!$A$4:$A$123,0)),"")) | E9: =IF($A9="","",IFERROR(INDEX('06-Precificacao'!$I$4:$I$123,MATCH($A9,'06-Precificacao'!$A$4:$A$123,0)),0)) | F9: =IF($A9="","",IFERROR(INDEX('06-Precificacao'!$K$4:$K$123,MATCH($A9,'06-Precificacao'!$A$4:$A$123,0)),0)) | H9: =IF(OR($A9="",$G9=""),"",$E9-$G9) | I9: =IF(OR($A9="",$G9="",$E9=0),"",$H9/$E9) | J9: =IF(OR($A9="",$G9=""),"",IF($G9<$F9,"SIM - abaixo do LP","Não")) | K9: =IF(OR($A9="",$G9=""),"",$G9-(IFERROR(INDEX('06-Precificacao'!$G$4:$G$123,MATCH($A9,'06-Precificacao'!$A$4:$A$123,0)),0)-IFERROR(INDEX('06-Precificacao'!$E$4:$E$123,MATCH($A9,'06-Precificacao'!$A$4:$A$123,0)),0)+IFERROR(INDEX('05-Financeiro'!$E$4:$E$123,MATCH($A9,'05-Financeiro'!$A$4:$A$123,0)),0))-($G9*'00-Parametros'!$C$9)-($G9*'00-Parametros'!$C$10)-IFERROR(INDEX('03-Marketing'!$C$4:$C$123,MATCH($A9,'03-Marketing'!$A$4:$A$123,0)),0)-($G9*'00-Parametros'!$C$12)) | L9: =IF(OR($A9="",$G9="",$G9=0),"",$K9/$G9)
B10: =IF($A10="","",IFERROR(INDEX('01-Cadastro-Motos'!$B$4:$B$123,MATCH($A10,'01-Cadastro-Motos'!$A$4:$A$123,0)),"")) | E10: =IF($A10="","",IFERROR(INDEX('06-Precificacao'!$I$4:$I$123,MATCH($A10,'06-Precificacao'!$A$4:$A$123,0)),0)) | F10: =IF($A10="","",IFERROR(INDEX('06-Precificacao'!$K$4:$K$123,MATCH($A10,'06-Precificacao'!$A$4:$A$123,0)),0)) | H10: =IF(OR($A10="",$G10=""),"",$E10-$G10) | I10: =IF(OR($A10="",$G10="",$E10=0),"",$H10/$E10) | J10: =IF(OR($A10="",$G10=""),"",IF($G10<$F10,"SIM - abaixo do LP","Não")) | K10: =IF(OR($A10="",$G10=""),"",$G10-(IFERROR(INDEX('06-Precificacao'!$G$4:$G$123,MATCH($A10,'06-Precificacao'!$A$4:$A$123,0)),0)-IFERROR(INDEX('06-Precificacao'!$E$4:$E$123,MATCH($A10,'06-Precificacao'!$A$4:$A$123,0)),0)+IFERROR(INDEX('05-Financeiro'!$E$4:$E$123,MATCH($A10,'05-Financeiro'!$A$4:$A$123,0)),0))-($G10*'00-Parametros'!$C$9)-($G10*'00-Parametros'!$C$10)-IFERROR(INDEX('03-Marketing'!$C$4:$C$123,MATCH($A10,'03-Marketing'!$A$4:$A$123,0)),0)-($G10*'00-Parametros'!$C$12)) | L10: =IF(OR($A10="",$G10="",$G10=0),"",$K10/$G10)
B11: =IF($A11="","",IFERROR(INDEX('01-Cadastro-Motos'!$B$4:$B$123,MATCH($A11,'01-Cadastro-Motos'!$A$4:$A$123,0)),"")) | E11: =IF($A11="","",IFERROR(INDEX('06-Precificacao'!$I$4:$I$123,MATCH($A11,'06-Precificacao'!$A$4:$A$123,0)),0)) | F11: =IF($A11="","",IFERROR(INDEX('06-Precificacao'!$K$4:$K$123,MATCH($A11,'06-Precificacao'!$A$4:$A$123,0)),0)) | H11: =IF(OR($A11="",$G11=""),"",$E11-$G11) | I11: =IF(OR($A11="",$G11="",$E11=0),"",$H11/$E11) | J11: =IF(OR($A11="",$G11=""),"",IF($G11<$F11,"SIM - abaixo do LP","Não")) | K11: =IF(OR($A11="",$G11=""),"",$G11-(IFERROR(INDEX('06-Precificacao'!$G$4:$G$123,MATCH($A11,'06-Precificacao'!$A$4:$A$123,0)),0)-IFERROR(INDEX('06-Precificacao'!$E$4:$E$123,MATCH($A11,'06-Precificacao'!$A$4:$A$123,0)),0)+IFERROR(INDEX('05-Financeiro'!$E$4:$E$123,MATCH($A11,'05-Financeiro'!$A$4:$A$123,0)),0))-($G11*'00-Parametros'!$C$9)-($G11*'00-Parametros'!$C$10)-IFERROR(INDEX('03-Marketing'!$C$4:$C$123,MATCH($A11,'03-Marketing'!$A$4:$A$123,0)),0)-($G11*'00-Parametros'!$C$12)) | L11: =IF(OR($A11="",$G11="",$G11=0),"",$K11/$G11)
B12: =IF($A12="","",IFERROR(INDEX('01-Cadastro-Motos'!$B$4:$B$123,MATCH($A12,'01-Cadastro-Motos'!$A$4:$A$123,0)),"")) | E12: =IF($A12="","",IFERROR(INDEX('06-Precificacao'!$I$4:$I$123,MATCH($A12,'06-Precificacao'!$A$4:$A$123,0)),0)) | F12: =IF($A12="","",IFERROR(INDEX('06-Precificacao'!$K$4:$K$123,MATCH($A12,'06-Precificacao'!$A$4:$A$123,0)),0)) | H12: =IF(OR($A12="",$G12=""),"",$E12-$G12) | I12: =IF(OR($A12="",$G12="",$E12=0),"",$H12/$E12) | J12: =IF(OR($A12="",$G12=""),"",IF($G12<$F12,"SIM - abaixo do LP","Não")) | K12: =IF(OR($A12="",$G12=""),"",$G12-(IFERROR(INDEX('06-Precificacao'!$G$4:$G$123,MATCH($A12,'06-Precificacao'!$A$4:$A$123,0)),0)-IFERROR(INDEX('06-Precificacao'!$E$4:$E$123,MATCH($A12,'06-Precificacao'!$A$4:$A$123,0)),0)+IFERROR(INDEX('05-Financeiro'!$E$4:$E$123,MATCH($A12,'05-Financeiro'!$A$4:$A$123,0)),0))-($G12*'00-Parametros'!$C$9)-($G12*'00-Parametros'!$C$10)-IFERROR(INDEX('03-Marketing'!$C$4:$C$123,MATCH($A12,'03-Marketing'!$A$4:$A$123,0)),0)-($G12*'00-Parametros'!$C$12)) | L12: =IF(OR($A12="",$G12="",$G12=0),"",$K12/$G12)
B13: =IF($A13="","",IFERROR(INDEX('01-Cadastro-Motos'!$B$4:$B$123,MATCH($A13,'01-Cadastro-Motos'!$A$4:$A$123,0)),"")) | E13: =IF($A13="","",IFERROR(INDEX('06-Precificacao'!$I$4:$I$123,MATCH($A13,'06-Precificacao'!$A$4:$A$123,0)),0)) | F13: =IF($A13="","",IFERROR(INDEX('06-Precificacao'!$K$4:$K$123,MATCH($A13,'06-Precificacao'!$A$4:$A$123,0)),0)) | H13: =IF(OR($A13="",$G13=""),"",$E13-$G13) | I13: =IF(OR($A13="",$G13="",$E13=0),"",$H13/$E13) | J13: =IF(OR($A13="",$G13=""),"",IF($G13<$F13,"SIM - abaixo do LP","Não")) | K13: =IF(OR($A13="",$G13=""),"",$G13-(IFERROR(INDEX('06-Precificacao'!$G$4:$G$123,MATCH($A13,'06-Precificacao'!$A$4:$A$123,0)),0)-IFERROR(INDEX('06-Precificacao'!$E$4:$E$123,MATCH($A13,'06-Precificacao'!$A$4:$A$123,0)),0)+IFERROR(INDEX('05-Financeiro'!$E$4:$E$123,MATCH($A13,'05-Financeiro'!$A$4:$A$123,0)),0))-($G13*'00-Parametros'!$C$9)-($G13*'00-Parametros'!$C$10)-IFERROR(INDEX('03-Marketing'!$C$4:$C$123,MATCH($A13,'03-Marketing'!$A$4:$A$123,0)),0)-($G13*'00-Parametros'!$C$12)) | L13: =IF(OR($A13="",$G13="",$G13=0),"",$K13/$G13)
B14: =IF($A14="","",IFERROR(INDEX('01-Cadastro-Motos'!$B$4:$B$123,MATCH($A14,'01-Cadastro-Motos'!$A$4:$A$123,0)),"")) | E14: =IF($A14="","",IFERROR(INDEX('06-Precificacao'!$I$4:$I$123,MATCH($A14,'06-Precificacao'!$A$4:$A$123,0)),0)) | F14: =IF($A14="","",IFERROR(INDEX('06-Precificacao'!$K$4:$K$123,MATCH($A14,'06-Precificacao'!$A$4:$A$123,0)),0)) | H14: =IF(OR($A14="",$G14=""),"",$E14-$G14) | I14: =IF(OR($A14="",$G14="",$E14=0),"",$H14/$E14) | J14: =IF(OR($A14="",$G14=""),"",IF($G14<$F14,"SIM - abaixo do LP","Não")) | K14: =IF(OR($A14="",$G14=""),"",$G14-(IFERROR(INDEX('06-Precificacao'!$G$4:$G$123,MATCH($A14,'06-Precificacao'!$A$4:$A$123,0)),0)-IFERROR(INDEX('06-Precificacao'!$E$4:$E$123,MATCH($A14,'06-Precificacao'!$A$4:$A$123,0)),0)+IFERROR(INDEX('05-Financeiro'!$E$4:$E$123,MATCH($A14,'05-Financeiro'!$A$4:$A$123,0)),0))-($G14*'00-Parametros'!$C$9)-($G14*'00-Parametros'!$C$10)-IFERROR(INDEX('03-Marketing'!$C$4:$C$123,MATCH($A14,'03-Marketing'!$A$4:$A$123,0)),0)-($G14*'00-Parametros'!$C$12)) | L14: =IF(OR($A14="",$G14="",$G14=0),"",$K14/$G14)
B15: =IF($A15="","",IFERROR(INDEX('01-Cadastro-Motos'!$B$4:$B$123,MATCH($A15,'01-Cadastro-Motos'!$A$4:$A$123,0)),"")) | E15: =IF($A15="","",IFERROR(INDEX('06-Precificacao'!$I$4:$I$123,MATCH($A15,'06-Precificacao'!$A$4:$A$123,0)),0)) | F15: =IF($A15="","",IFERROR(INDEX('06-Precificacao'!$K$4:$K$123,MATCH($A15,'06-Precificacao'!$A$4:$A$123,0)),0)) | H15: =IF(OR($A15="",$G15=""),"",$E15-$G15) | I15: =IF(OR($A15="",$G15="",$E15=0),"",$H15/$E15) | J15: =IF(OR($A15="",$G15=""),"",IF($G15<$F15,"SIM - abaixo do LP","Não")) | K15: =IF(OR($A15="",$G15=""),"",$G15-(IFERROR(INDEX('06-Precificacao'!$G$4:$G$123,MATCH($A15,'06-Precificacao'!$A$4:$A$123,0)),0)-IFERROR(INDEX('06-Precificacao'!$E$4:$E$123,MATCH($A15,'06-Precificacao'!$A$4:$A$123,0)),0)+IFERROR(INDEX('05-Financeiro'!$E$4:$E$123,MATCH($A15,'05-Financeiro'!$A$4:$A$123,0)),0))-($G15*'00-Parametros'!$C$9)-($G15*'00-Parametros'!$C$10)-IFERROR(INDEX('03-Marketing'!$C$4:$C$123,MATCH($A15,'03-Marketing'!$A$4:$A$123,0)),0)-($G15*'00-Parametros'!$C$12)) | L15: =IF(OR($A15="",$G15="",$G15=0),"",$K15/$G15)
B16: =IF($A16="","",IFERROR(INDEX('01-Cadastro-Motos'!$B$4:$B$123,MATCH($A16,'01-Cadastro-Motos'!$A$4:$A$123,0)),"")) | E16: =IF($A16="","",IFERROR(INDEX('06-Precificacao'!$I$4:$I$123,MATCH($A16,'06-Precificacao'!$A$4:$A$123,0)),0)) | F16: =IF($A16="","",IFERROR(INDEX('06-Precificacao'!$K$4:$K$123,MATCH($A16,'06-Precificacao'!$A$4:$A$123,0)),0)) | H16: =IF(OR($A16="",$G16=""),"",$E16-$G16) | I16: =IF(OR($A16="",$G16="",$E16=0),"",$H16/$E16) | J16: =IF(OR($A16="",$G16=""),"",IF($G16<$F16,"SIM - abaixo do LP","Não")) | K16: =IF(OR($A16="",$G16=""),"",$G16-(IFERROR(INDEX('06-Precificacao'!$G$4:$G$123,MATCH($A16,'06-Precificacao'!$A$4:$A$123,0)),0)-IFERROR(INDEX('06-Precificacao'!$E$4:$E$123,MATCH($A16,'06-Precificacao'!$A$4:$A$123,0)),0)+IFERROR(INDEX('05-Financeiro'!$E$4:$E$123,MATCH($A16,'05-Financeiro'!$A$4:$A$123,0)),0))-($G16*'00-Parametros'!$C$9)-($G16*'00-Parametros'!$C$10)-IFERROR(INDEX('03-Marketing'!$C$4:$C$123,MATCH($A16,'03-Marketing'!$A$4:$A$123,0)),0)-($G16*'00-Parametros'!$C$12)) | L16: =IF(OR($A16="",$G16="",$G16=0),"",$K16/$G16)
... B123: =IF($A123="","",IFERROR(INDEX('01-Cadastro-Motos'!$B$4:$B$123,MATCH($A123,'01-Cadastro-Motos'!$A$4:$A$123,0)),"")) | E123: =IF($A123="","",IFERROR(INDEX('06-Precificacao'!$I$4:$I$123,MATCH($A123,'06-Precificacao'!$A$4:$A$123,0)),0)) | F123: =IF($A123="","",IFERROR(INDEX('06-Precificacao'!$K$4:$K$123,MATCH($A123,'06-Precificacao'!$A$4:$A$123,0)),0)) | H123: =IF(OR($A123="",$G123=""),"",$E123-$G123) | I123: =IF(OR($A123="",$G123="",$E123=0),"",$H123/$E123) | J123: =IF(OR($A123="",$G123=""),"",IF($G123<$F123,"SIM - abaixo do LP","Não")) | K123: =IF(OR($A123="",$G123=""),"",$G123-(IFERROR(INDEX('06-Precificacao'!$G$4:$G$123,MATCH($A123,'06-Precificacao'!$A$4:$A$123,0)),0)-IFERROR(INDEX('06-Precificacao'!$E$4:$E$123,MATCH($A123,'06-Precificacao'!$A$4:$A$123,0)),0)+IFERROR(INDEX('05-Financeiro'!$E$4:$E$123,MATCH($A123,'05-Financeiro'!$A$4:$A$123,0)),0))-($G123*'00-Parametros'!$C$9)-($G123*'00-Parametros'!$C$10)-IFERROR(INDEX('03-Marketing'!$C$4:$C$123,MATCH($A123,'03-Marketing'!$A$4:$A$123,0)),0)-($G123*'00-Parametros'!$C$12)) | L123: =IF(OR($A123="",$G123="",$G123=0),"",$K123/$G123)

Sheet 09-Ranking-Vendedores
A1: Performance Comercial por Vendedor (Pilar 7)
A3: ID Vendedor | B3: Nome (auto) | C3: Qtde Vendas | D3: Ticket Médio (R$) | E3: Desconto Médio (%) | F3: Margem Líquida Média Realizada (%) | G3: Lucro Total Entregue (R$) | H3: % Vendas no Preço Cheio+ | I3: Ranking Financeiro | J3: Ranking Comercial
A4: =IF('04-Comercial'!$A4="","",'04-Comercial'!$A4) | B4: =IF($A4="","",IFERROR(INDEX('04-Comercial'!$B$4:$B$33,MATCH($A4,'04-Comercial'!$A$4:$A$33,0)),"")) | C4: =IF($A4="","",COUNTIF('08-Vendas-Negociacao'!$C$4:$C$123,$A4)) | D4: =IF(OR($A4="",$C4=0),"",AVERAGEIF('08-Vendas-Negociacao'!$C$4:$C$123,$A4,'08-Vendas-Negociacao'!$G$4:$G$123)) | E4: =IF(OR($A4="",$C4=0),"",AVERAGEIF('08-Vendas-Negociacao'!$C$4:$C$123,$A4,'08-Vendas-Negociacao'!$I$4:$I$123)) | F4: =IF(OR($A4="",$C4=0),"",AVERAGEIF('08-Vendas-Negociacao'!$C$4:$C$123,$A4,'08-Vendas-Negociacao'!$L$4:$L$123)) | G4: =IF(OR($A4="",$C4=0),"",SUMIF('08-Vendas-Negociacao'!$C$4:$C$123,$A4,'08-Vendas-Negociacao'!$K$4:$K$123)) | H4: =IF(OR($A4="",$C4=0),"",SUMPRODUCT(('08-Vendas-Negociacao'!$C$4:$C$123=$A4)*('08-Vendas-Negociacao'!$G$4:$G$123>='08-Vendas-Negociacao'!$E$4:$E$123))/$C4) | I4: =IF(OR($A4="",$G4=""),"",RANK($G4,$G$4:$G$33)) | J4: =IF(OR($A4="",$C4=0),"",RANK($C4,$C$4:$C$33))
A5: =IF('04-Comercial'!$A5="","",'04-Comercial'!$A5) | B5: =IF($A5="","",IFERROR(INDEX('04-Comercial'!$B$4:$B$33,MATCH($A5,'04-Comercial'!$A$4:$A$33,0)),"")) | C5: =IF($A5="","",COUNTIF('08-Vendas-Negociacao'!$C$4:$C$123,$A5)) | D5: =IF(OR($A5="",$C5=0),"",AVERAGEIF('08-Vendas-Negociacao'!$C$4:$C$123,$A5,'08-Vendas-Negociacao'!$G$4:$G$123)) | E5: =IF(OR($A5="",$C5=0),"",AVERAGEIF('08-Vendas-Negociacao'!$C$4:$C$123,$A5,'08-Vendas-Negociacao'!$I$4:$I$123)) | F5: =IF(OR($A5="",$C5=0),"",AVERAGEIF('08-Vendas-Negociacao'!$C$4:$C$123,$A5,'08-Vendas-Negociacao'!$L$4:$L$123)) | G5: =IF(OR($A5="",$C5=0),"",SUMIF('08-Vendas-Negociacao'!$C$4:$C$123,$A5,'08-Vendas-Negociacao'!$K$4:$K$123)) | H5: =IF(OR($A5="",$C5=0),"",SUMPRODUCT(('08-Vendas-Negociacao'!$C$4:$C$123=$A5)*('08-Vendas-Negociacao'!$G$4:$G$123>='08-Vendas-Negociacao'!$E$4:$E$123))/$C5) | I5: =IF(OR($A5="",$G5=""),"",RANK($G5,$G$4:$G$33)) | J5: =IF(OR($A5="",$C5=0),"",RANK($C5,$C$4:$C$33))
A6: =IF('04-Comercial'!$A6="","",'04-Comercial'!$A6) | B6: =IF($A6="","",IFERROR(INDEX('04-Comercial'!$B$4:$B$33,MATCH($A6,'04-Comercial'!$A$4:$A$33,0)),"")) | C6: =IF($A6="","",COUNTIF('08-Vendas-Negociacao'!$C$4:$C$123,$A6)) | D6: =IF(OR($A6="",$C6=0),"",AVERAGEIF('08-Vendas-Negociacao'!$C$4:$C$123,$A6,'08-Vendas-Negociacao'!$G$4:$G$123)) | E6: =IF(OR($A6="",$C6=0),"",AVERAGEIF('08-Vendas-Negociacao'!$C$4:$C$123,$A6,'08-Vendas-Negociacao'!$I$4:$I$123)) | F6: =IF(OR($A6="",$C6=0),"",AVERAGEIF('08-Vendas-Negociacao'!$C$4:$C$123,$A6,'08-Vendas-Negociacao'!$L$4:$L$123)) | G6: =IF(OR($A6="",$C6=0),"",SUMIF('08-Vendas-Negociacao'!$C$4:$C$123,$A6,'08-Vendas-Negociacao'!$K$4:$K$123)) | H6: =IF(OR($A6="",$C6=0),"",SUMPRODUCT(('08-Vendas-Negociacao'!$C$4:$C$123=$A6)*('08-Vendas-Negociacao'!$G$4:$G$123>='08-Vendas-Negociacao'!$E$4:$E$123))/$C6) | I6: =IF(OR($A6="",$G6=""),"",RANK($G6,$G$4:$G$33)) | J6: =IF(OR($A6="",$C6=0),"",RANK($C6,$C$4:$C$33))
A7: =IF('04-Comercial'!$A7="","",'04-Comercial'!$A7) | B7: =IF($A7="","",IFERROR(INDEX('04-Comercial'!$B$4:$B$33,MATCH($A7,'04-Comercial'!$A$4:$A$33,0)),"")) | C7: =IF($A7="","",COUNTIF('08-Vendas-Negociacao'!$C$4:$C$123,$A7)) | D7: =IF(OR($A7="",$C7=0),"",AVERAGEIF('08-Vendas-Negociacao'!$C$4:$C$123,$A7,'08-Vendas-Negociacao'!$G$4:$G$123)) | E7: =IF(OR($A7="",$C7=0),"",AVERAGEIF('08-Vendas-Negociacao'!$C$4:$C$123,$A7,'08-Vendas-Negociacao'!$I$4:$I$123)) | F7: =IF(OR($A7="",$C7=0),"",AVERAGEIF('08-Vendas-Negociacao'!$C$4:$C$123,$A7,'08-Vendas-Negociacao'!$L$4:$L$123)) | G7: =IF(OR($A7="",$C7=0),"",SUMIF('08-Vendas-Negociacao'!$C$4:$C$123,$A7,'08-Vendas-Negociacao'!$K$4:$K$123)) | H7: =IF(OR($A7="",$C7=0),"",SUMPRODUCT(('08-Vendas-Negociacao'!$C$4:$C$123=$A7)*('08-Vendas-Negociacao'!$G$4:$G$123>='08-Vendas-Negociacao'!$E$4:$E$123))/$C7) | I7: =IF(OR($A7="",$G7=""),"",RANK($G7,$G$4:$G$33)) | J7: =IF(OR($A7="",$C7=0),"",RANK($C7,$C$4:$C$33))
A8: =IF('04-Comercial'!$A8="","",'04-Comercial'!$A8) | B8: =IF($A8="","",IFERROR(INDEX('04-Comercial'!$B$4:$B$33,MATCH($A8,'04-Comercial'!$A$4:$A$33,0)),"")) | C8: =IF($A8="","",COUNTIF('08-Vendas-Negociacao'!$C$4:$C$123,$A8)) | D8: =IF(OR($A8="",$C8=0),"",AVERAGEIF('08-Vendas-Negociacao'!$C$4:$C$123,$A8,'08-Vendas-Negociacao'!$G$4:$G$123)) | E8: =IF(OR($A8="",$C8=0),"",AVERAGEIF('08-Vendas-Negociacao'!$C$4:$C$123,$A8,'08-Vendas-Negociacao'!$I$4:$I$123)) | F8: =IF(OR($A8="",$C8=0),"",AVERAGEIF('08-Vendas-Negociacao'!$C$4:$C$123,$A8,'08-Vendas-Negociacao'!$L$4:$L$123)) | G8: =IF(OR($A8="",$C8=0),"",SUMIF('08-Vendas-Negociacao'!$C$4:$C$123,$A8,'08-Vendas-Negociacao'!$K$4:$K$123)) | H8: =IF(OR($A8="",$C8=0),"",SUMPRODUCT(('08-Vendas-Negociacao'!$C$4:$C$123=$A8)*('08-Vendas-Negociacao'!$G$4:$G$123>='08-Vendas-Negociacao'!$E$4:$E$123))/$C8) | I8: =IF(OR($A8="",$G8=""),"",RANK($G8,$G$4:$G$33)) | J8: =IF(OR($A8="",$C8=0),"",RANK($C8,$C$4:$C$33))
A9: =IF('04-Comercial'!$A9="","",'04-Comercial'!$A9) | B9: =IF($A9="","",IFERROR(INDEX('04-Comercial'!$B$4:$B$33,MATCH($A9,'04-Comercial'!$A$4:$A$33,0)),"")) | C9: =IF($A9="","",COUNTIF('08-Vendas-Negociacao'!$C$4:$C$123,$A9)) | D9: =IF(OR($A9="",$C9=0),"",AVERAGEIF('08-Vendas-Negociacao'!$C$4:$C$123,$A9,'08-Vendas-Negociacao'!$G$4:$G$123)) | E9: =IF(OR($A9="",$C9=0),"",AVERAGEIF('08-Vendas-Negociacao'!$C$4:$C$123,$A9,'08-Vendas-Negociacao'!$I$4:$I$123)) | F9: =IF(OR($A9="",$C9=0),"",AVERAGEIF('08-Vendas-Negociacao'!$C$4:$C$123,$A9,'08-Vendas-Negociacao'!$L$4:$L$123)) | G9: =IF(OR($A9="",$C9=0),"",SUMIF('08-Vendas-Negociacao'!$C$4:$C$123,$A9,'08-Vendas-Negociacao'!$K$4:$K$123)) | H9: =IF(OR($A9="",$C9=0),"",SUMPRODUCT(('08-Vendas-Negociacao'!$C$4:$C$123=$A9)*('08-Vendas-Negociacao'!$G$4:$G$123>='08-Vendas-Negociacao'!$E$4:$E$123))/$C9) | I9: =IF(OR($A9="",$G9=""),"",RANK($G9,$G$4:$G$33)) | J9: =IF(OR($A9="",$C9=0),"",RANK($C9,$C$4:$C$33))
A10: =IF('04-Comercial'!$A10="","",'04-Comercial'!$A10) | B10: =IF($A10="","",IFERROR(INDEX('04-Comercial'!$B$4:$B$33,MATCH($A10,'04-Comercial'!$A$4:$A$33,0)),"")) | C10: =IF($A10="","",COUNTIF('08-Vendas-Negociacao'!$C$4:$C$123,$A10)) | D10: =IF(OR($A10="",$C10=0),"",AVERAGEIF('08-Vendas-Negociacao'!$C$4:$C$123,$A10,'08-Vendas-Negociacao'!$G$4:$G$123)) | E10: =IF(OR($A10="",$C10=0),"",AVERAGEIF('08-Vendas-Negociacao'!$C$4:$C$123,$A10,'08-Vendas-Negociacao'!$I$4:$I$123)) | F10: =IF(OR($A10="",$C10=0),"",AVERAGEIF('08-Vendas-Negociacao'!$C$4:$C$123,$A10,'08-Vendas-Negociacao'!$L$4:$L$123)) | G10: =IF(OR($A10="",$C10=0),"",SUMIF('08-Vendas-Negociacao'!$C$4:$C$123,$A10,'08-Vendas-Negociacao'!$K$4:$K$123)) | H10: =IF(OR($A10="",$C10=0),"",SUMPRODUCT(('08-Vendas-Negociacao'!$C$4:$C$123=$A10)*('08-Vendas-Negociacao'!$G$4:$G$123>='08-Vendas-Negociacao'!$E$4:$E$123))/$C10) | I10: =IF(OR($A10="",$G10=""),"",RANK($G10,$G$4:$G$33)) | J10: =IF(OR($A10="",$C10=0),"",RANK($C10,$C$4:$C$33))
A11: =IF('04-Comercial'!$A11="","",'04-Comercial'!$A11) | B11: =IF($A11="","",IFERROR(INDEX('04-Comercial'!$B$4:$B$33,MATCH($A11,'04-Comercial'!$A$4:$A$33,0)),"")) | C11: =IF($A11="","",COUNTIF('08-Vendas-Negociacao'!$C$4:$C$123,$A11)) | D11: =IF(OR($A11="",$C11=0),"",AVERAGEIF('08-Vendas-Negociacao'!$C$4:$C$123,$A11,'08-Vendas-Negociacao'!$G$4:$G$123)) | E11: =IF(OR($A11="",$C11=0),"",AVERAGEIF('08-Vendas-Negociacao'!$C$4:$C$123,$A11,'08-Vendas-Negociacao'!$I$4:$I$123)) | F11: =IF(OR($A11="",$C11=0),"",AVERAGEIF('08-Vendas-Negociacao'!$C$4:$C$123,$A11,'08-Vendas-Negociacao'!$L$4:$L$123)) | G11: =IF(OR($A11="",$C11=0),"",SUMIF('08-Vendas-Negociacao'!$C$4:$C$123,$A11,'08-Vendas-Negociacao'!$K$4:$K$123)) | H11: =IF(OR($A11="",$C11=0),"",SUMPRODUCT(('08-Vendas-Negociacao'!$C$4:$C$123=$A11)*('08-Vendas-Negociacao'!$G$4:$G$123>='08-Vendas-Negociacao'!$E$4:$E$123))/$C11) | I11: =IF(OR($A11="",$G11=""),"",RANK($G11,$G$4:$G$33)) | J11: =IF(OR($A11="",$C11=0),"",RANK($C11,$C$4:$C$33))
A12: =IF('04-Comercial'!$A12="","",'04-Comercial'!$A12) | B12: =IF($A12="","",IFERROR(INDEX('04-Comercial'!$B$4:$B$33,MATCH($A12,'04-Comercial'!$A$4:$A$33,0)),"")) | C12: =IF($A12="","",COUNTIF('08-Vendas-Negociacao'!$C$4:$C$123,$A12)) | D12: =IF(OR($A12="",$C12=0),"",AVERAGEIF('08-Vendas-Negociacao'!$C$4:$C$123,$A12,'08-Vendas-Negociacao'!$G$4:$G$123)) | E12: =IF(OR($A12="",$C12=0),"",AVERAGEIF('08-Vendas-Negociacao'!$C$4:$C$123,$A12,'08-Vendas-Negociacao'!$I$4:$I$123)) | F12: =IF(OR($A12="",$C12=0),"",AVERAGEIF('08-Vendas-Negociacao'!$C$4:$C$123,$A12,'08-Vendas-Negociacao'!$L$4:$L$123)) | G12: =IF(OR($A12="",$C12=0),"",SUMIF('08-Vendas-Negociacao'!$C$4:$C$123,$A12,'08-Vendas-Negociacao'!$K$4:$K$123)) | H12: =IF(OR($A12="",$C12=0),"",SUMPRODUCT(('08-Vendas-Negociacao'!$C$4:$C$123=$A12)*('08-Vendas-Negociacao'!$G$4:$G$123>='08-Vendas-Negociacao'!$E$4:$E$123))/$C12) | I12: =IF(OR($A12="",$G12=""),"",RANK($G12,$G$4:$G$33)) | J12: =IF(OR($A12="",$C12=0),"",RANK($C12,$C$4:$C$33))
A13: =IF('04-Comercial'!$A13="","",'04-Comercial'!$A13) | B13: =IF($A13="","",IFERROR(INDEX('04-Comercial'!$B$4:$B$33,MATCH($A13,'04-Comercial'!$A$4:$A$33,0)),"")) | C13: =IF($A13="","",COUNTIF('08-Vendas-Negociacao'!$C$4:$C$123,$A13)) | D13: =IF(OR($A13="",$C13=0),"",AVERAGEIF('08-Vendas-Negociacao'!$C$4:$C$123,$A13,'08-Vendas-Negociacao'!$G$4:$G$123)) | E13: =IF(OR($A13="",$C13=0),"",AVERAGEIF('08-Vendas-Negociacao'!$C$4:$C$123,$A13,'08-Vendas-Negociacao'!$I$4:$I$123)) | F13: =IF(OR($A13="",$C13=0),"",AVERAGEIF('08-Vendas-Negociacao'!$C$4:$C$123,$A13,'08-Vendas-Negociacao'!$L$4:$L$123)) | G13: =IF(OR($A13="",$C13=0),"",SUMIF('08-Vendas-Negociacao'!$C$4:$C$123,$A13,'08-Vendas-Negociacao'!$K$4:$K$123)) | H13: =IF(OR($A13="",$C13=0),"",SUMPRODUCT(('08-Vendas-Negociacao'!$C$4:$C$123=$A13)*('08-Vendas-Negociacao'!$G$4:$G$123>='08-Vendas-Negociacao'!$E$4:$E$123))/$C13) | I13: =IF(OR($A13="",$G13=""),"",RANK($G13,$G$4:$G$33)) | J13: =IF(OR($A13="",$C13=0),"",RANK($C13,$C$4:$C$33))
A14: =IF('04-Comercial'!$A14="","",'04-Comercial'!$A14) | B14: =IF($A14="","",IFERROR(INDEX('04-Comercial'!$B$4:$B$33,MATCH($A14,'04-Comercial'!$A$4:$A$33,0)),"")) | C14: =IF($A14="","",COUNTIF('08-Vendas-Negociacao'!$C$4:$C$123,$A14)) | D14: =IF(OR($A14="",$C14=0),"",AVERAGEIF('08-Vendas-Negociacao'!$C$4:$C$123,$A14,'08-Vendas-Negociacao'!$G$4:$G$123)) | E14: =IF(OR($A14="",$C14=0),"",AVERAGEIF('08-Vendas-Negociacao'!$C$4:$C$123,$A14,'08-Vendas-Negociacao'!$I$4:$I$123)) | F14: =IF(OR($A14="",$C14=0),"",AVERAGEIF('08-Vendas-Negociacao'!$C$4:$C$123,$A14,'08-Vendas-Negociacao'!$L$4:$L$123)) | G14: =IF(OR($A14="",$C14=0),"",SUMIF('08-Vendas-Negociacao'!$C$4:$C$123,$A14,'08-Vendas-Negociacao'!$K$4:$K$123)) | H14: =IF(OR($A14="",$C14=0),"",SUMPRODUCT(('08-Vendas-Negociacao'!$C$4:$C$123=$A14)*('08-Vendas-Negociacao'!$G$4:$G$123>='08-Vendas-Negociacao'!$E$4:$E$123))/$C14) | I14: =IF(OR($A14="",$G14=""),"",RANK($G14,$G$4:$G$33)) | J14: =IF(OR($A14="",$C14=0),"",RANK($C14,$C$4:$C$33))
A15: =IF('04-Comercial'!$A15="","",'04-Comercial'!$A15) | B15: =IF($A15="","",IFERROR(INDEX('04-Comercial'!$B$4:$B$33,MATCH($A15,'04-Comercial'!$A$4:$A$33,0)),"")) | C15: =IF($A15="","",COUNTIF('08-Vendas-Negociacao'!$C$4:$C$123,$A15)) | D15: =IF(OR($A15="",$C15=0),"",AVERAGEIF('08-Vendas-Negociacao'!$C$4:$C$123,$A15,'08-Vendas-Negociacao'!$G$4:$G$123)) | E15: =IF(OR($A15="",$C15=0),"",AVERAGEIF('08-Vendas-Negociacao'!$C$4:$C$123,$A15,'08-Vendas-Negociacao'!$I$4:$I$123)) | F15: =IF(OR($A15="",$C15=0),"",AVERAGEIF('08-Vendas-Negociacao'!$C$4:$C$123,$A15,'08-Vendas-Negociacao'!$L$4:$L$123)) | G15: =IF(OR($A15="",$C15=0),"",SUMIF('08-Vendas-Negociacao'!$C$4:$C$123,$A15,'08-Vendas-Negociacao'!$K$4:$K$123)) | H15: =IF(OR($A15="",$C15=0),"",SUMPRODUCT(('08-Vendas-Negociacao'!$C$4:$C$123=$A15)*('08-Vendas-Negociacao'!$G$4:$G$123>='08-Vendas-Negociacao'!$E$4:$E$123))/$C15) | I15: =IF(OR($A15="",$G15=""),"",RANK($G15,$G$4:$G$33)) | J15: =IF(OR($A15="",$C15=0),"",RANK($C15,$C$4:$C$33))
... A33: =IF('04-Comercial'!$A33="","",'04-Comercial'!$A33) | B33: =IF($A33="","",IFERROR(INDEX('04-Comercial'!$B$4:$B$33,MATCH($A33,'04-Comercial'!$A$4:$A$33,0)),"")) | C33: =IF($A33="","",COUNTIF('08-Vendas-Negociacao'!$C$4:$C$123,$A33)) | D33: =IF(OR($A33="",$C33=0),"",AVERAGEIF('08-Vendas-Negociacao'!$C$4:$C$123,$A33,'08-Vendas-Negociacao'!$G$4:$G$123)) | E33: =IF(OR($A33="",$C33=0),"",AVERAGEIF('08-Vendas-Negociacao'!$C$4:$C$123,$A33,'08-Vendas-Negociacao'!$I$4:$I$123)) | F33: =IF(OR($A33="",$C33=0),"",AVERAGEIF('08-Vendas-Negociacao'!$C$4:$C$123,$A33,'08-Vendas-Negociacao'!$L$4:$L$123)) | G33: =IF(OR($A33="",$C33=0),"",SUMIF('08-Vendas-Negociacao'!$C$4:$C$123,$A33,'08-Vendas-Negociacao'!$K$4:$K$123)) | H33: =IF(OR($A33="",$C33=0),"",SUMPRODUCT(('08-Vendas-Negociacao'!$C$4:$C$123=$A33)*('08-Vendas-Negociacao'!$G$4:$G$123>='08-Vendas-Negociacao'!$E$4:$E$123))/$C33) | I33: =IF(OR($A33="",$G33=""),"",RANK($G33,$G$4:$G$33)) | J33: =IF(OR($A33="",$C33=0),"",RANK($C33,$C$4:$C$33))

Sheet 10-Indicadores-KPIs
A1: Indicadores e KPIs Consolidados da Operação (Pilares 4, 8, 10)
A3: # | B3: Indicador | C3: Valor | D3: Fórmula / Origem
A4: 1 | B4: Lucro Médio por Moto Vendida (R$) | C4: =IFERROR(AVERAGEIF('08-Vendas-Negociacao'!$G$4:$G$123,">0",'08-Vendas-Negociacao'!$K$4:$K$123),0) | D4: Calculado automaticamente a partir de 06/07/08
A5: 2 | B5: Margem Líquida Média Realizada (%) | C5: =IFERROR(AVERAGEIF('08-Vendas-Negociacao'!$G$4:$G$123,">0",'08-Vendas-Negociacao'!$L$4:$L$123),0) | D5: Calculado automaticamente a partir de 06/07/08
A6: 3 | B6: Desconto Médio Praticado (%) | C6: =IFERROR(AVERAGEIF('08-Vendas-Negociacao'!$G$4:$G$123,">0",'08-Vendas-Negociacao'!$I$4:$I$123),0) | D6: Calculado automaticamente a partir de 06/07/08
A7: 4 | B7: Capital Investido Total em Estoque (R$) | C7: =SUMIF('01-Cadastro-Motos'!$K$4:$K$123,"<>Vendida",'01-Cadastro-Motos'!$I$4:$I$123) | D7: Calculado automaticamente a partir de 06/07/08
A8: 5 | B8: Capital Parado (Atenção + Crítico) (R$) | C8: =SUMIF('07-Estoque-Dinamica'!$F$4:$F$123,"Estoque Atenção",'07-Estoque-Dinamica'!$H$4:$H$123)+SUMIF('07-Estoque-Dinamica'!$F$4:$F$123,"Estoque Crítico",'07-Estoque-Dinamica'!$H$4:$H$123) | D8: Calculado automaticamente a partir de 06/07/08
A9: 6 | B9: Tempo Médio em Estoque — motos vendidas (dias) | C9: =IFERROR(AVERAGEIF('01-Cadastro-Motos'!$K$4:$K$123,"Vendida",'01-Cadastro-Motos'!$P$4:$P$123),0) | D9: Calculado automaticamente a partir de 06/07/08
A10: 7 | B10: Nº de Motos acima de 90 dias (Fase 4) | C10: =COUNTIF('07-Estoque-Dinamica'!$D$4:$D$123,">90") | D10: Calculado automaticamente a partir de 06/07/08
A11: 8 | B11: Nº de Motos em Estoque Crítico | C11: =COUNTIF('07-Estoque-Dinamica'!$F$4:$F$123,"Estoque Crítico") | D11: Calculado automaticamente a partir de 06/07/08
A12: 9 | B12: Nº de Motos em Estoque Premium | C12: =COUNTIF('07-Estoque-Dinamica'!$F$4:$F$123,"Estoque Premium") | D12: Calculado automaticamente a partir de 06/07/08
A13: 10 | B13: % de Vendas no Preço Comercial ou Acima | C13: =IFERROR(SUMPRODUCT(('08-Vendas-Negociacao'!$G$4:$G$123<>"")*('08-Vendas-Negociacao'!$G$4:$G$123>='08-Vendas-Negociacao'!$E$4:$E$123))/SUMPRODUCT(('08-Vendas-Negociacao'!$G$4:$G$123<>"")*1),0) | D13: Calculado automaticamente a partir de 06/07/08
A14: 11 | B14: Nº de Vendas Abaixo do LP (não-conformidades) | C14: =COUNTIF('08-Vendas-Negociacao'!$J$4:$J$123,"SIM - abaixo do LP") | D14: Calculado automaticamente a partir de 06/07/08
A15: 12 | B15: ROI Médio (sobre motos vendidas) | C15: =IFERROR(AVERAGEIF('08-Vendas-Negociacao'!$G$4:$G$123,">0",'08-Vendas-Negociacao'!$K$4:$K$123)/AVERAGEIF('08-Vendas-Negociacao'!$G$4:$G$123,">0",'06-Precificacao'!$G$4:$G$123),0) | D15: Calculado automaticamente a partir de 06/07/08

Sheet 11-Curva-ABC
A1: Curva ABC do Estoque por Contribuição de Lucro
A2: Nota: ordene manualmente a coluna 'Lucro Gerado' (maior→menor) antes de ler o % Acumulado — a Curva ABC exige ordenação decrescente.
A3: ID Moto | B3: Modelo (auto) | C3: Lucro Gerado (R$) | D3: % do Lucro Total | E3: % Acumulado | F3: Classe
A4: =IF('01-Cadastro-Motos'!$A4="","",'01-Cadastro-Motos'!$A4) | B4: =IF($A4="","",IFERROR(INDEX('01-Cadastro-Motos'!$B$4:$B$123,MATCH($A4,'01-Cadastro-Motos'!$A$4:$A$123,0)),"")) | C4: =IF($A4="","",IFERROR(INDEX('08-Vendas-Negociacao'!$K$4:$K$123,MATCH($A4,'08-Vendas-Negociacao'!$A$4:$A$123,0)),0)) | D4: =IF(OR($A4="",SUM($C$4:$C$123)=0),"",$C4/SUM($C$4:$C$123)) | E4: =IF($A4="","",SUM($D$4:$D4)) | F4: =IF(OR($A4="",$C4=0),"N/A - não vendida",IF($E4<=0.8,"A",IF($E4<=0.95,"B","C")))
A5: =IF('01-Cadastro-Motos'!$A5="","",'01-Cadastro-Motos'!$A5) | B5: =IF($A5="","",IFERROR(INDEX('01-Cadastro-Motos'!$B$4:$B$123,MATCH($A5,'01-Cadastro-Motos'!$A$4:$A$123,0)),"")) | C5: =IF($A5="","",IFERROR(INDEX('08-Vendas-Negociacao'!$K$4:$K$123,MATCH($A5,'08-Vendas-Negociacao'!$A$4:$A$123,0)),0)) | D5: =IF(OR($A5="",SUM($C$4:$C$123)=0),"",$C5/SUM($C$4:$C$123)) | E5: =IF($A5="","",SUM($D$4:$D5)) | F5: =IF(OR($A5="",$C5=0),"N/A - não vendida",IF($E5<=0.8,"A",IF($E5<=0.95,"B","C")))
A6: =IF('01-Cadastro-Motos'!$A6="","",'01-Cadastro-Motos'!$A6) | B6: =IF($A6="","",IFERROR(INDEX('01-Cadastro-Motos'!$B$4:$B$123,MATCH($A6,'01-Cadastro-Motos'!$A$4:$A$123,0)),"")) | C6: =IF($A6="","",IFERROR(INDEX('08-Vendas-Negociacao'!$K$4:$K$123,MATCH($A6,'08-Vendas-Negociacao'!$A$4:$A$123,0)),0)) | D6: =IF(OR($A6="",SUM($C$4:$C$123)=0),"",$C6/SUM($C$4:$C$123)) | E6: =IF($A6="","",SUM($D$4:$D6)) | F6: =IF(OR($A6="",$C6=0),"N/A - não vendida",IF($E6<=0.8,"A",IF($E6<=0.95,"B","C")))
A7: =IF('01-Cadastro-Motos'!$A7="","",'01-Cadastro-Motos'!$A7) | B7: =IF($A7="","",IFERROR(INDEX('01-Cadastro-Motos'!$B$4:$B$123,MATCH($A7,'01-Cadastro-Motos'!$A$4:$A$123,0)),"")) | C7: =IF($A7="","",IFERROR(INDEX('08-Vendas-Negociacao'!$K$4:$K$123,MATCH($A7,'08-Vendas-Negociacao'!$A$4:$A$123,0)),0)) | D7: =IF(OR($A7="",SUM($C$4:$C$123)=0),"",$C7/SUM($C$4:$C$123)) | E7: =IF($A7="","",SUM($D$4:$D7)) | F7: =IF(OR($A7="",$C7=0),"N/A - não vendida",IF($E7<=0.8,"A",IF($E7<=0.95,"B","C")))
A8: =IF('01-Cadastro-Motos'!$A8="","",'01-Cadastro-Motos'!$A8) | B8: =IF($A8="","",IFERROR(INDEX('01-Cadastro-Motos'!$B$4:$B$123,MATCH($A8,'01-Cadastro-Motos'!$A$4:$A$123,0)),"")) | C8: =IF($A8="","",IFERROR(INDEX('08-Vendas-Negociacao'!$K$4:$K$123,MATCH($A8,'08-Vendas-Negociacao'!$A$4:$A$123,0)),0)) | D8: =IF(OR($A8="",SUM($C$4:$C$123)=0),"",$C8/SUM($C$4:$C$123)) | E8: =IF($A8="","",SUM($D$4:$D8)) | F8: =IF(OR($A8="",$C8=0),"N/A - não vendida",IF($E8<=0.8,"A",IF($E8<=0.95,"B","C")))
A9: =IF('01-Cadastro-Motos'!$A9="","",'01-Cadastro-Motos'!$A9) | B9: =IF($A9="","",IFERROR(INDEX('01-Cadastro-Motos'!$B$4:$B$123,MATCH($A9,'01-Cadastro-Motos'!$A$4:$A$123,0)),"")) | C9: =IF($A9="","",IFERROR(INDEX('08-Vendas-Negociacao'!$K$4:$K$123,MATCH($A9,'08-Vendas-Negociacao'!$A$4:$A$123,0)),0)) | D9: =IF(OR($A9="",SUM($C$4:$C$123)=0),"",$C9/SUM($C$4:$C$123)) | E9: =IF($A9="","",SUM($D$4:$D9)) | F9: =IF(OR($A9="",$C9=0),"N/A - não vendida",IF($E9<=0.8,"A",IF($E9<=0.95,"B","C")))
A10: =IF('01-Cadastro-Motos'!$A10="","",'01-Cadastro-Motos'!$A10) | B10: =IF($A10="","",IFERROR(INDEX('01-Cadastro-Motos'!$B$4:$B$123,MATCH($A10,'01-Cadastro-Motos'!$A$4:$A$123,0)),"")) | C10: =IF($A10="","",IFERROR(INDEX('08-Vendas-Negociacao'!$K$4:$K$123,MATCH($A10,'08-Vendas-Negociacao'!$A$4:$A$123,0)),0)) | D10: =IF(OR($A10="",SUM($C$4:$C$123)=0),"",$C10/SUM($C$4:$C$123)) | E10: =IF($A10="","",SUM($D$4:$D10)) | F10: =IF(OR($A10="",$C10=0),"N/A - não vendida",IF($E10<=0.8,"A",IF($E10<=0.95,"B","C")))
A11: =IF('01-Cadastro-Motos'!$A11="","",'01-Cadastro-Motos'!$A11) | B11: =IF($A11="","",IFERROR(INDEX('01-Cadastro-Motos'!$B$4:$B$123,MATCH($A11,'01-Cadastro-Motos'!$A$4:$A$123,0)),"")) | C11: =IF($A11="","",IFERROR(INDEX('08-Vendas-Negociacao'!$K$4:$K$123,MATCH($A11,'08-Vendas-Negociacao'!$A$4:$A$123,0)),0)) | D11: =IF(OR($A11="",SUM($C$4:$C$123)=0),"",$C11/SUM($C$4:$C$123)) | E11: =IF($A11="","",SUM($D$4:$D11)) | F11: =IF(OR($A11="",$C11=0),"N/A - não vendida",IF($E11<=0.8,"A",IF($E11<=0.95,"B","C")))
A12: =IF('01-Cadastro-Motos'!$A12="","",'01-Cadastro-Motos'!$A12) | B12: =IF($A12="","",IFERROR(INDEX('01-Cadastro-Motos'!$B$4:$B$123,MATCH($A12,'01-Cadastro-Motos'!$A$4:$A$123,0)),"")) | C12: =IF($A12="","",IFERROR(INDEX('08-Vendas-Negociacao'!$K$4:$K$123,MATCH($A12,'08-Vendas-Negociacao'!$A$4:$A$123,0)),0)) | D12: =IF(OR($A12="",SUM($C$4:$C$123)=0),"",$C12/SUM($C$4:$C$123)) | E12: =IF($A12="","",SUM($D$4:$D12)) | F12: =IF(OR($A12="",$C12=0),"N/A - não vendida",IF($E12<=0.8,"A",IF($E12<=0.95,"B","C")))
A13: =IF('01-Cadastro-Motos'!$A13="","",'01-Cadastro-Motos'!$A13) | B13: =IF($A13="","",IFERROR(INDEX('01-Cadastro-Motos'!$B$4:$B$123,MATCH($A13,'01-Cadastro-Motos'!$A$4:$A$123,0)),"")) | C13: =IF($A13="","",IFERROR(INDEX('08-Vendas-Negociacao'!$K$4:$K$123,MATCH($A13,'08-Vendas-Negociacao'!$A$4:$A$123,0)),0)) | D13: =IF(OR($A13="",SUM($C$4:$C$123)=0),"",$C13/SUM($C$4:$C$123)) | E13: =IF($A13="","",SUM($D$4:$D13)) | F13: =IF(OR($A13="",$C13=0),"N/A - não vendida",IF($E13<=0.8,"A",IF($E13<=0.95,"B","C")))
A14: =IF('01-Cadastro-Motos'!$A14="","",'01-Cadastro-Motos'!$A14) | B14: =IF($A14="","",IFERROR(INDEX('01-Cadastro-Motos'!$B$4:$B$123,MATCH($A14,'01-Cadastro-Motos'!$A$4:$A$123,0)),"")) | C14: =IF($A14="","",IFERROR(INDEX('08-Vendas-Negociacao'!$K$4:$K$123,MATCH($A14,'08-Vendas-Negociacao'!$A$4:$A$123,0)),0)) | D14: =IF(OR($A14="",SUM($C$4:$C$123)=0),"",$C14/SUM($C$4:$C$123)) | E14: =IF($A14="","",SUM($D$4:$D14)) | F14: =IF(OR($A14="",$C14=0),"N/A - não vendida",IF($E14<=0.8,"A",IF($E14<=0.95,"B","C")))
A15: =IF('01-Cadastro-Motos'!$A15="","",'01-Cadastro-Motos'!$A15) | B15: =IF($A15="","",IFERROR(INDEX('01-Cadastro-Motos'!$B$4:$B$123,MATCH($A15,'01-Cadastro-Motos'!$A$4:$A$123,0)),"")) | C15: =IF($A15="","",IFERROR(INDEX('08-Vendas-Negociacao'!$K$4:$K$123,MATCH($A15,'08-Vendas-Negociacao'!$A$4:$A$123,0)),0)) | D15: =IF(OR($A15="",SUM($C$4:$C$123)=0),"",$C15/SUM($C$4:$C$123)) | E15: =IF($A15="","",SUM($D$4:$D15)) | F15: =IF(OR($A15="",$C15=0),"N/A - não vendida",IF($E15<=0.8,"A",IF($E15<=0.95,"B","C")))
... A123: =IF('01-Cadastro-Motos'!$A123="","",'01-Cadastro-Motos'!$A123) | B123: =IF($A123="","",IFERROR(INDEX('01-Cadastro-Motos'!$B$4:$B$123,MATCH($A123,'01-Cadastro-Motos'!$A$4:$A$123,0)),"")) | C123: =IF($A123="","",IFERROR(INDEX('08-Vendas-Negociacao'!$K$4:$K$123,MATCH($A123,'08-Vendas-Negociacao'!$A$4:$A$123,0)),0)) | D123: =IF(OR($A123="",SUM($C$4:$C$123)=0),"",$C123/SUM($C$4:$C$123)) | E123: =IF($A123="","",SUM($D$4:$D123)) | F123: =IF(OR($A123="",$C123=0),"N/A - não vendida",IF($E123<=0.8,"A",IF($E123<=0.95,"B","C")))

Sheet 12-Governanca-Historico
A1: Histórico de Alterações de Preço e Governança (Pilar 9)
A3: Data | B3: ID Moto | C3: Preço Anterior (R$) | D3: Preço Novo (R$) | E3: Margem Utilizada | F3: Motivo | G3: Solicitante | H3: Aprovador | I3: Nível de Aprovação | J3: Registrado?
J4: =IF($I4="","",IF(OR($I4="N2",$I4="N3"),IF(AND($G4<>"",$H4<>""),"Completo","PENDENTE"),"N/A"))
J5: =IF($I5="","",IF(OR($I5="N2",$I5="N3"),IF(AND($G5<>"",$H5<>""),"Completo","PENDENTE"),"N/A"))
J6: =IF($I6="","",IF(OR($I6="N2",$I6="N3"),IF(AND($G6<>"",$H6<>""),"Completo","PENDENTE"),"N/A"))
J7: =IF($I7="","",IF(OR($I7="N2",$I7="N3"),IF(AND($G7<>"",$H7<>""),"Completo","PENDENTE"),"N/A"))
J8: =IF($I8="","",IF(OR($I8="N2",$I8="N3"),IF(AND($G8<>"",$H8<>""),"Completo","PENDENTE"),"N/A"))
J9: =IF($I9="","",IF(OR($I9="N2",$I9="N3"),IF(AND($G9<>"",$H9<>""),"Completo","PENDENTE"),"N/A"))
J10: =IF($I10="","",IF(OR($I10="N2",$I10="N3"),IF(AND($G10<>"",$H10<>""),"Completo","PENDENTE"),"N/A"))
J11: =IF($I11="","",IF(OR($I11="N2",$I11="N3"),IF(AND($G11<>"",$H11<>""),"Completo","PENDENTE"),"N/A"))
J12: =IF($I12="","",IF(OR($I12="N2",$I12="N3"),IF(AND($G12<>"",$H12<>""),"Completo","PENDENTE"),"N/A"))
J13: =IF($I13="","",IF(OR($I13="N2",$I13="N3"),IF(AND($G13<>"",$H13<>""),"Completo","PENDENTE"),"N/A"))
J14: =IF($I14="","",IF(OR($I14="N2",$I14="N3"),IF(AND($G14<>"",$H14<>""),"Completo","PENDENTE"),"N/A"))
J15: =IF($I15="","",IF(OR($I15="N2",$I15="N3"),IF(AND($G15<>"",$H15<>""),"Completo","PENDENTE"),"N/A"))
... J123: =IF($I123="","",IF(OR($I123="N2",$I123="N3"),IF(AND($G123<>"",$H123<>""),"Completo","PENDENTE"),"N/A"))

Sheet 13-Dashboard
A1: DASHBOARD EXECUTIVO — MM Negócios Veículos
A2: Visão CEO / CFO / Diretor Comercial (Pilar 13)
A4: INDICADORES FINANCEIROS
A5: Lucro Médio por Moto Vendida (R$) | C5: ='10-Indicadores-KPIs'!C4
A6: Margem Líquida Média Realizada (%) | C6: ='10-Indicadores-KPIs'!C5
A7: Capital Investido Total em Estoque (R$) | C7: ='10-Indicadores-KPIs'!C7
A8: Capital Parado (Atenção + Crítico) (R$) | C8: ='10-Indicadores-KPIs'!C8
A9: ROI Médio (sobre motos vendidas) | C9: ='10-Indicadores-KPIs'!C15
A11: INDICADORES COMERCIAIS E DE ESTOQUE
A12: Desconto Médio Praticado (%) | C12: ='10-Indicadores-KPIs'!C6
A13: Tempo Médio em Estoque — motos vendidas (dias) | C13: ='10-Indicadores-KPIs'!C9
A14: Nº de Motos acima de 90 dias (Fase 4) | C14: ='10-Indicadores-KPIs'!C10
A15: Nº de Motos em Estoque Crítico | C15: ='10-Indicadores-KPIs'!C11
A16: Nº de Motos em Estoque Premium | C16: ='10-Indicadores-KPIs'!C12
A17: % de Vendas no Preço Comercial ou Acima | C17: ='10-Indicadores-KPIs'!C13
A18: Nº de Vendas Abaixo do LP (não-conformidades) | C18: ='10-Indicadores-KPIs'!C14
A21: RESUMO PARA GRÁFICOS (não editar)
A22: Fase do Ciclo | B22: Qtde Motos
A23: Fase 1 - Lançamento (0-30) | B23: =COUNTIF('07-Estoque-Dinamica'!$E$4:$E$123,"Fase 1 - Lançamento (0-30)")
A24: Fase 2 - Consolidação (31-60) | B24: =COUNTIF('07-Estoque-Dinamica'!$E$4:$E$123,"Fase 2 - Consolidação (31-60)")
A25: Fase 3 - Aceleração de Giro (61-90) | B25: =COUNTIF('07-Estoque-Dinamica'!$E$4:$E$123,"Fase 3 - Aceleração de Giro (61-90)")
A26: Fase 4 - Estoque Envelhecido (>90) | B26: =COUNTIF('07-Estoque-Dinamica'!$E$4:$E$123,"Fase 4 - Estoque Envelhecido (>90)")
A28: Vendedor | B28: Lucro Total Entregue (R$)
A29: ='09-Ranking-Vendedores'!B4 | B29: ='09-Ranking-Vendedores'!G4
A30: ='09-Ranking-Vendedores'!B5 | B30: ='09-Ranking-Vendedores'!G5
A31: ='09-Ranking-Vendedores'!B6 | B31: ='09-Ranking-Vendedores'!G6
A32: ='09-Ranking-Vendedores'!B7 | B32: ='09-Ranking-Vendedores'!G7
A33: ='09-Ranking-Vendedores'!B8 | B33: ='09-Ranking-Vendedores'!G8
A34: ='09-Ranking-Vendedores'!B9 | B34: ='09-Ranking-Vendedores'!G9
A35: ='09-Ranking-Vendedores'!B10 | B35: ='09-Ranking-Vendedores'!G10
A36: ='09-Ranking-Vendedores'!B11 | B36: ='09-Ranking-Vendedores'!G11
A37: ='09-Ranking-Vendedores'!B12 | B37: ='09-Ranking-Vendedores'!G12
A38: ='09-Ranking-Vendedores'!B13 | B38: ='09-Ranking-Vendedores'!G13
